{
    "type": "FeatureCollection",
    "features": [
        {
            "id": 61884,
            "type": "Feature",
            "geometry": {
                "type": "Point",
                "coordinates": [
                    20.83528,
                    51.46199
                ]
            },
            "properties": {
                "isced:level": "1;2",
                "ref:rspo": 61884,
                "official_name": "Publiczna Szko\u0142a Podstawowa im. Or\u0142a Bia\u0142ego we Wrzosie",
                "name": "Publiczna Szko\u0142a Podstawowa",
                "addr:postcode": "26-650",
                "addr:place": "Wrzos",
                "addr:housenumber": "6",
                "addr:teryt:simc": 634590,
                "phone": "+48 486180028",
                "email": "pspwrzos@wp.pl",
                "website": "http:\/\/www.pspwrzos.pl",
                "ref:regon": "001145835",
                "ref:vatin": "PL9482604088",
                "operator": "Gmina Przytyk",
                "operator:type": "government",
                "amenity": "school"
            }
        },
        {
            "id": 62433,
            "type": "Feature",
            "geometry": {
                "type": "Point",
                "coordinates": [
                    20.9036,
                    51.47163
                ]
            },
            "properties": {
                "ref:rspo": 62433,
                "official_name": "Publiczne Przedszkole w Przytyku",
                "name": "Publiczne Przedszkole w Przytyku",
                "addr:postcode": "26-650",
                "addr:city": "Przytyk",
                "addr:street": "Stefana \u017beromskiego",
                "addr:housenumber": "11",
                "addr:teryt:simc": 634348,
                "addr:teryt:sym_ul": 26469,
                "phone": "+48 483121050",
                "email": "przedszkoleprzytyk@gmail.com",
                "website": "http:\/\/www.przedszkoleprzytyk.pl",
                "ref:regon": "672981871",
                "ref:vatin": "PL9482604094",
                "operator": "Gmina Przytyk",
                "operator:type": "government",
                "amenity": "kindergarten"
            }
        },
        {
            "id": 58174,
            "type": "Feature",
            "geometry": {
                "type": "Point",
                "coordinates": [
                    20.90487,
                    51.47197
                ]
            },
            "properties": {
                "isced:level": "1;2",
                "ref:rspo": 58174,
                "official_name": "Publiczna Szko\u0142a Podstawowa im. Przyjaci\u00f3\u0142 Dzieci w Przytyku",
                "name": "Publiczna Szko\u0142a Podstawowa",
                "addr:postcode": "26-650",
                "addr:city": "Przytyk",
                "addr:street": "Szkolna",
                "addr:housenumber": "3",
                "addr:teryt:simc": 634348,
                "addr:teryt:sym_ul": 21970,
                "phone": "+48 486180352",
                "email": "pspprzytyk@poczta.onet.pl",
                "ref:regon": "000271526",
                "ref:vatin": "PL7981076494",
                "operator": "Gmina Przytyk",
                "operator:type": "government",
                "amenity": "school"
            }
        },
        {
            "id": 61883,
            "type": "Feature",
            "geometry": {
                "type": "Point",
                "coordinates": [
                    20.82743,
                    51.49767
                ]
            },
            "properties": {
                "isced:level": "1;2",
                "ref:rspo": 61883,
                "official_name": "Publiczna Szko\u0142a Podstawowa \nIm. Kornela Makuszy\u0144skiego\nWe Wrzeszczowie",
                "name": "Publiczna Szko\u0142a Podstawowa \nIm. Kornela Makuszy\u0144skiego\nWe Wrzeszczowie",
                "addr:postcode": "26-650",
                "addr:place": "Wrzeszcz\u00f3w",
                "addr:housenumber": "47",
                "addr:teryt:simc": 634578,
                "phone": "+48 486180103",
                "email": "pspwrzeszcz@poczta.onet.pl",
                "website": "http:\/\/pspwrzeszczow.szkolnastrona.pl",
                "ref:regon": "001145670",
                "ref:vatin": "PL7981076494",
                "operator": "Gmina Przytyk",
                "operator:type": "government",
                "amenity": "school"
            }
        }
    ]
}