{
    "type": "FeatureCollection",
    "features": [
        {
            "id": 44017,
            "type": "Feature",
            "geometry": {
                "type": "Point",
                "coordinates": [
                    21.51775,
                    54.21541
                ]
            },
            "properties": {
                "isced:level": "1;2",
                "ref:rspo": 44017,
                "official_name": "Szko\u0142a Podstawowa im. Prof. Stanis\u0142awa Srokowskiego w Srokowie",
                "name": "Szko\u0142a Podstawowa",
                "addr:postcode": "11-420",
                "addr:city": "Srokowo",
                "addr:street": "Szkolna",
                "addr:housenumber": "3",
                "addr:teryt:simc": 488668,
                "addr:teryt:sym_ul": 21970,
                "phone": "+48 897534001",
                "email": "dyrektor@spsrokowo.pl",
                "website": "http:\/\/www.spsrokowo.edu.pl",
                "ref:regon": "000665403",
                "ref:vatin": "PL7421858847",
                "operator": "Gmina Srokowo",
                "operator:type": "government",
                "amenity": "school"
            }
        }
    ]
}