{
    "type": "FeatureCollection",
    "features": [
        {
            "id": 111550,
            "type": "Feature",
            "geometry": {
                "type": "Point",
                "coordinates": [
                    14.73753,
                    51.53224
                ]
            },
            "properties": {
                "ref:rspo": 111550,
                "official_name": "Przedszkole Miejskie w \u0141\u0119knicy",
                "name": "Przedszkole Miejskie w \u0141\u0119knicy",
                "addr:country": "PL",
                "addr:postcode": "68-208",
                "addr:city": "\u0141\u0119knica",
                "addr:street": "ul. Tadeusza Ko\u015bciuszki",
                "addr:housenumber": "1",
                "addr:teryt:simc": 9582,
                "addr:teryt:sym_ul": 988508,
                "contact:phone": "+48 683753054",
                "contact:email": "pmleknica@wp.pl",
                "contact:website": "http:\/\/www.zspleknica.info",
                "ref:regon": "000240804",
                "ref:vatin": "PL9281732164",
                "operator": "Gmina \u0141\u0119knica",
                "operator:type": "government",
                "amenity": "kindergarten",
                "note": "Parent RSPO: 4170"
            }
        },
        {
            "id": 4170,
            "type": "Feature",
            "geometry": {
                "type": "Point",
                "coordinates": [
                    14.73679,
                    51.53298
                ]
            },
            "properties": {
                "ref:rspo": 4170,
                "official_name": "Zesp\u00f3\u0142 Szk\u00f3\u0142 Publicznych w \u0141\u0119knicy",
                "name": "Zesp\u00f3\u0142 Szk\u00f3\u0142 Publicznych w \u0141\u0119knicy",
                "addr:country": "PL",
                "addr:postcode": "68-208",
                "addr:city": "\u0141\u0119knica",
                "addr:street": "ul. Wojska Polskiego",
                "addr:housenumber": "19A",
                "addr:teryt:simc": 24628,
                "addr:teryt:sym_ul": 988508,
                "contact:phone": "+48 683753023",
                "contact:email": "zeaoleknica@zspleknica.info",
                "contact:website": "http:\/\/zspleknica.info",
                "ref:regon": "080340127",
                "ref:vatin": "PL9282037928",
                "operator": "Gmina \u0141\u0119knica",
                "operator:type": "government",
                "landuse": "education",
                "fixme": "amenity=school, amenity=college albo landuse=education w zale\u017cno\u015bci od tego, jakie plac\u00f3wki wchodz\u0105 w sk\u0142ad zespo\u0142u. Sprawd\u017a, kiedy stosowa\u0107 amenity=* a kiedy landuse=education.",
                "note": "Children RSPO: 53770;111550"
            }
        },
        {
            "id": 53770,
            "type": "Feature",
            "geometry": {
                "type": "Point",
                "coordinates": [
                    14.73679,
                    51.53295
                ]
            },
            "properties": {
                "isced:level": "1;2",
                "ref:rspo": 53770,
                "official_name": "Szko\u0142a Podstawowa im.jana Brzechwy w \u0141\u0119knicy",
                "name": "Szko\u0142a Podstawowa im.jana Brzechwy w \u0141\u0119knicy",
                "addr:country": "PL",
                "addr:postcode": "68-208",
                "addr:city": "\u0141\u0119knica",
                "addr:street": "ul. Wojska Polskiego",
                "addr:housenumber": "19A",
                "addr:teryt:simc": 24628,
                "addr:teryt:sym_ul": 988508,
                "contact:phone": "+48 683753023",
                "contact:email": "spleknica@wp.pl",
                "contact:website": "http:\/\/www.spleknica.info",
                "ref:regon": "970570634",
                "ref:vatin": "PL9281732170",
                "operator": "Gmina \u0141\u0119knica",
                "operator:type": "government",
                "amenity": "school",
                "note": "Parent RSPO: 4170"
            }
        }
    ]
}