{
    "type": "FeatureCollection",
    "features": [
        {
            "id": 85772,
            "type": "Feature",
            "geometry": {
                "type": "Point",
                "coordinates": [
                    18.55187,
                    53.88121
                ]
            },
            "properties": {
                "isced:level": "1;2",
                "ref:rspo": 85772,
                "official_name": "Publiczna Szko\u0142a Podstawowa im. Jana Paw\u0142a II w Bobowie",
                "name": "Publiczna Szko\u0142a Podstawowa",
                "addr:postcode": "83-212",
                "addr:city": "Bobowo",
                "addr:street": "Gimnazjalna",
                "addr:housenumber": "20",
                "addr:teryt:simc": 159491,
                "addr:teryt:sym_ul": 5527,
                "phone": "+48 585621722",
                "email": "szkola@bobowo.pl",
                "website": "http:\/\/zsp.bobowo.nazwa.pl",
                "ref:regon": "192967546",
                "ref:vatin": "PL5922056359",
                "operator": "Gmina Bobowo",
                "operator:type": "government",
                "amenity": "school"
            }
        },
        {
            "id": 64519,
            "type": "Feature",
            "geometry": {
                "type": "Point",
                "coordinates": [
                    18.55756,
                    53.88793
                ]
            },
            "properties": {
                "ref:rspo": 64519,
                "official_name": "Przedszkole Publiczne w Bobowie",
                "name": "Przedszkole Publiczne w Bobowie",
                "addr:postcode": "83-212",
                "addr:city": "Bobowo",
                "addr:street": "Gda\u0144ska",
                "addr:housenumber": "17",
                "addr:teryt:simc": 159491,
                "addr:teryt:sym_ul": 5431,
                "phone": "+48 585621766",
                "email": "przedszkole@bobowo.pl",
                "website": "http:\/\/bobowo.pl\/przedszkole-publiczne-w-bobowie\/",
                "ref:regon": "190601670",
                "ref:vatin": "PL5922131210",
                "operator": "Gmina Bobowo",
                "operator:type": "government",
                "amenity": "kindergarten"
            }
        },
        {
            "id": 273215,
            "type": "Feature",
            "geometry": {
                "type": "Point",
                "coordinates": [
                    18.55756,
                    53.887899999999995
                ]
            },
            "properties": {
                "ref:rspo": 273215,
                "official_name": "Punkt Przedszkolny Przy Przedszkolu Publicznym w Bobowie",
                "name": "Punkt Przedszkolny Przy Przedszkolu Publicznym w Bobowie",
                "addr:postcode": "83-212",
                "addr:city": "Bobowo",
                "addr:street": "Gda\u0144ska",
                "addr:housenumber": "17",
                "addr:teryt:simc": 159491,
                "addr:teryt:sym_ul": 5431,
                "phone": "+48 585621766",
                "email": "przedszkole@bobowo.pl",
                "website": "http:\/\/bobowo.pl",
                "ref:regon": "384405788",
                "operator": "Gmina Bobowo",
                "operator:type": "government",
                "amenity": "kindergarten"
            }
        }
    ]
}