{
    "type": "FeatureCollection",
    "features": [
        {
            "id": 24440,
            "type": "Feature",
            "geometry": {
                "type": "Point",
                "coordinates": [
                    23.67136,
                    53.09256
                ]
            },
            "properties": {
                "ref:rspo": 24440,
                "official_name": "Przedszkole Samorzadowe w Gr\u00f3dku",
                "name": "Przedszkole Samorzadowe w Gr\u00f3dku",
                "addr:country": "PL",
                "addr:postcode": "16-040",
                "addr:city": "Gr\u00f3dek",
                "addr:street": "ul. Fabryczna",
                "addr:housenumber": "8",
                "addr:teryt:simc": 4863,
                "addr:teryt:sym_ul": 29015,
                "contact:phone": "+48 857180133",
                "contact:email": "przedszkole@grodek.pl",
                "contact:website": "http:\/\/www.przedszkolewgrodku.cba.pl",
                "ref:regon": "000942699",
                "ref:vatin": "PL9661484198",
                "operator": "Gmina Gr\u00f3dek",
                "operator:type": "government",
                "amenity": "kindergarten"
            }
        },
        {
            "id": 24437,
            "type": "Feature",
            "geometry": {
                "type": "Point",
                "coordinates": [
                    23.67657,
                    53.0930899
                ]
            },
            "properties": {
                "isced:level": "1;2",
                "ref:rspo": 24437,
                "official_name": "Szko\u0142a Podstawowa Imienia Partyzant\u00f3w Braci Micha\u0142a I Aleksandra Chrzanowskich w Gr\u00f3dku",
                "name": "Szko\u0142a Podstawowa Imienia Partyzant\u00f3w Braci Micha\u0142a I Aleksandra Chrzanowskich w Gr\u00f3dku",
                "addr:country": "PL",
                "addr:postcode": "16-040",
                "addr:city": "Gr\u00f3dek",
                "addr:street": "ul. Aleksandra i Grzegorza Chodkiewicz\u00f3w",
                "addr:housenumber": "18",
                "addr:teryt:simc": 27090,
                "addr:teryt:sym_ul": 29015,
                "contact:phone": "+48 857180233",
                "contact:email": "spgrodek@grodek.pl",
                "contact:website": "http:\/\/www.spgrodek.edu.pl",
                "ref:regon": "000558067",
                "ref:vatin": "PL9662085052",
                "operator": "Gmina Gr\u00f3dek",
                "operator:type": "government",
                "amenity": "school"
            }
        },
        {
            "id": 24442,
            "type": "Feature",
            "geometry": {
                "type": "Point",
                "coordinates": [
                    23.5495779,
                    53.155974
                ]
            },
            "properties": {
                "ref:rspo": 24442,
                "official_name": "Punkt Przedszkolny - \"O\u015brodek Wychowania Przedszkolnego Wed\u0142ug Marii Montesorii\" w Gminie Gr\u00f3dek",
                "name": "Punkt Przedszkolny - \"O\u015brodek Wychowania Przedszkolnego Wed\u0142ug Marii Montesorii\" w Gminie Gr\u00f3dek",
                "addr:country": "PL",
                "addr:postcode": "16-040",
                "addr:place": "Za\u0142uki",
                "addr:housenumber": "5",
                "addr:teryt:sym_ul": 29417,
                "contact:phone": "+48 857184402",
                "ref:regon": "200732748",
                "operator": "Gmina Gr\u00f3dek",
                "operator:type": "government",
                "amenity": "kindergarten"
            }
        },
        {
            "id": 62077,
            "type": "Feature",
            "geometry": {
                "type": "Point",
                "coordinates": [
                    23.5495779,
                    53.155944
                ]
            },
            "properties": {
                "isced:level": "1;2",
                "ref:rspo": 62077,
                "official_name": "Niepubliczna Szko\u0142a Podstawowa w Za\u0142ukach",
                "name": "Niepubliczna Szko\u0142a Podstawowa w Za\u0142ukach",
                "addr:country": "PL",
                "addr:postcode": "16-040",
                "addr:place": "Za\u0142uki",
                "addr:housenumber": "5",
                "addr:teryt:sym_ul": 29417,
                "contact:phone": "+48 857184402",
                "contact:email": "spzaluki@poczta.onet.pl",
                "contact:website": "http:\/\/www.nspzaluki.pl",
                "ref:regon": "200739012",
                "ref:vatin": "PL9661782688",
                "operator": "Stowarzyszenie \"Za\u0142uki Nad Supra\u015bl\u0105\"",
                "operator:type": "ngo",
                "amenity": "school"
            }
        }
    ]
}