{
    "type": "FeatureCollection",
    "features": [
        {
            "id": 53462,
            "type": "Feature",
            "geometry": {
                "type": "Point",
                "coordinates": [
                    14.502960205078,
                    35.87553024292
                ]
            },
            "properties": {
                "isced:level": "1;2",
                "ref:rspo": 53462,
                "official_name": "Szko\u0142a Podstawowa im. Jana Paw\u0142a II w Bielicach",
                "name": "Szko\u0142a Podstawowa",
                "addr:postcode": "74-202",
                "addr:city": "Bielice",
                "addr:street": "Jana Paw\u0142a II",
                "addr:housenumber": "33A",
                "addr:city:simc": 772843,
                "addr:street:sym_ul": 7123,
                "phone": "+48 915644127",
                "email": "sekretariat@sp.bielice.com.pl",
                "website": "http:\/\/spbielice.edupage.org",
                "ref:regon": "000595855",
                "operator": "Gmina Bielice",
                "operator:type": "government",
                "amenity": "school"
            }
        },
        {
            "id": 267136,
            "type": "Feature",
            "geometry": {
                "type": "Point",
                "coordinates": [
                    14.502960205078,
                    35.87550024292
                ]
            },
            "properties": {
                "ref:rspo": 267136,
                "official_name": "Oddzia\u0142y Przedszkolne w Szkole Podstawowej w Bielicach",
                "name": "Oddzia\u0142y Przedszkolne w Szkole Podstawowej w Bielicach",
                "addr:postcode": "74-202",
                "addr:city": "Bielice",
                "addr:street": "Jana Paw\u0142a II",
                "addr:housenumber": "33a",
                "addr:city:simc": 772843,
                "addr:street:sym_ul": 7123,
                "phone": "+48 915644127",
                "email": "sekretariat@sp.bielice.com.pl",
                "website": "http:\/\/spbielice.edupage.pl",
                "ref:regon": "369952111",
                "ref:vatin": "PL8531253494",
                "operator": "Gmina Bielice",
                "operator:type": "government",
                "amenity": "kindergarten"
            }
        },
        {
            "id": 276052,
            "type": "Feature",
            "geometry": {
                "type": "Point",
                "coordinates": [
                    14.72809,
                    53.20034
                ]
            },
            "properties": {
                "ref:rspo": 276052,
                "official_name": "Przedszkole Niepubliczne Towarzystwa Wiedzy Powszechnej Or w Szczecinie \"Ziarenko\" w Bielicach",
                "name": "Przedszkole Niepubliczne Towarzystwa Wiedzy Powszechnej Or w Szczecinie \"Ziarenko\" w Bielicach",
                "addr:postcode": "74-202",
                "addr:city": "Bielice",
                "addr:street": "Jana Paw\u0142a II",
                "addr:housenumber": "61A",
                "addr:city:simc": 772843,
                "addr:street:sym_ul": 7123,
                "phone": "+48 913112021",
                "email": "info@ziarenkobielice.pl",
                "website": "http:\/\/www.ziarenkobielice.edu.pl",
                "ref:regon": "386972758",
                "operator": "Towarzystwo Wiedzy Powszechnej Oddzia\u0142 Regionalny W Szczecinie",
                "operator:type": "ngo",
                "amenity": "kindergarten"
            }
        }
    ]
}