{
    "type": "FeatureCollection",
    "features": [
        {
            "id": 31092,
            "type": "Feature",
            "geometry": {
                "type": "Point",
                "coordinates": [
                    23.54707,
                    53.63312
                ]
            },
            "properties": {
                "isced:level": "1;2",
                "ref:rspo": 31092,
                "official_name": "Szko\u0142a Podstawowa w Nowym Dworze",
                "name": "Szko\u0142a Podstawowa w Nowym Dworze",
                "addr:postcode": "16-205",
                "addr:city": "Nowy Dw\u00f3r",
                "addr:street": "Kolejowa",
                "addr:housenumber": "2",
                "addr:city:simc": 37612,
                "addr:street:sym_ul": 8828,
                "phone": "+48 857226005",
                "email": "zsnd@op.pl",
                "website": "http:\/\/zsnowydwor.szkolna.net",
                "ref:regon": "000645464",
                "ref:vatin": "PL5451648912",
                "operator": "Gmina Nowy Dw\u00f3r",
                "operator:type": "government",
                "amenity": "school"
            }
        }
    ]
}