{
    "type": "FeatureCollection",
    "features": [
        {
            "id": 8034,
            "type": "Feature",
            "geometry": {
                "type": "Point",
                "coordinates": [
                    22.73006,
                    52.58003
                ]
            },
            "properties": {
                "ref:rspo": 8034,
                "official_name": "Zesp\u00f3\u0142 Szk\u00f3\u0142 w Grodzisku",
                "name": "Zesp\u00f3\u0142 Szk\u00f3\u0142 w Grodzisku",
                "addr:postcode": "17-315",
                "addr:city": "Grodzisk",
                "addr:street": "1 Maja",
                "addr:housenumber": "34",
                "addr:teryt:simc": 28553,
                "addr:teryt:sym_ul": 11926,
                "phone": "+48 856568481",
                "email": "szkola@zegrodzisk.pl",
                "website": "http:\/\/www.zsgrodzisk.edupage.org",
                "ref:regon": "052130512",
                "ref:vatin": "PL5441409850",
                "operator": "Gmina Grodzisk",
                "operator:type": "government",
                "landuse": "education",
                "fixme": "amenity=school, amenity=college albo landuse=education w zale\u017cno\u015bci od tego, jakie plac\u00f3wki wchodz\u0105 w sk\u0142ad zespo\u0142u. Sprawd\u017a, kiedy stosowa\u0107 amenity=* a kiedy landuse=education.",
                "note": "Children RSPO: 9557;130028"
            }
        },
        {
            "id": 9557,
            "type": "Feature",
            "geometry": {
                "type": "Point",
                "coordinates": [
                    22.73006,
                    52.58
                ]
            },
            "properties": {
                "isced:level": "1;2",
                "ref:rspo": 9557,
                "official_name": "Szko\u0142a Podstawowa im. Henryka Sienkiewicza w Grodzisku",
                "name": "Szko\u0142a Podstawowa",
                "addr:postcode": "17-315",
                "addr:city": "Grodzisk",
                "addr:street": "1 Maja",
                "addr:housenumber": "34",
                "addr:teryt:simc": 28553,
                "addr:teryt:sym_ul": 11926,
                "phone": "+48 856568481",
                "email": "szkola@zegrodzisk.pl",
                "website": "http:\/\/www.zsgrodzisk.edupage.org",
                "ref:regon": "000268850",
                "operator": "Gmina Grodzisk",
                "operator:type": "government",
                "amenity": "school",
                "note": "Parent RSPO: 8034"
            }
        },
        {
            "id": 130028,
            "type": "Feature",
            "geometry": {
                "type": "Point",
                "coordinates": [
                    22.73006,
                    52.57997
                ]
            },
            "properties": {
                "ref:rspo": 130028,
                "official_name": "Przedszkole w Grodzisku",
                "name": "Przedszkole w Grodzisku",
                "addr:postcode": "17-315",
                "addr:city": "Grodzisk",
                "addr:street": "1 Maja",
                "addr:housenumber": "34",
                "addr:teryt:simc": 28553,
                "addr:teryt:sym_ul": 11926,
                "phone": "+48 856568481",
                "email": "szkola@zegrodzisk.pl",
                "website": "http:\/\/www.zsgrodzisk.edupage.org",
                "ref:regon": "000942707",
                "operator": "Gmina Grodzisk",
                "operator:type": "government",
                "amenity": "kindergarten",
                "note": "Parent RSPO: 8034"
            }
        }
    ]
}