{"type":"FeatureCollection","features":[{"id":40080,"type":"Feature","geometry":{"type":"Point","coordinates":[16.87697,50.34317]},"properties":{"isced:level":"3","ref:rspo":40080,"official_name":"Liceum Og\u00f3lnokszta\u0142c\u0105ce im. Andrzeja Zawady w L\u0105dku-Zdroju","name":"Liceum Og\u00f3lnokszta\u0142c\u0105ce","addr:country":"PL","addr:postcode":"57-540","addr:city":"L\u0105dek-Zdr\u00f3j","addr:street":"ul. Polna","addr:housenumber":"2","addr:teryt:simc":17011,"addr:teryt:sym_ul":984203,"contact:phone":"+48 748146319","contact:email":"sekretariatlo@ladek.pl","ref:regon":"000832189","ref:vatin":"PL8811330244","operator":"Gmina L\u0105dek-Zdr\u00f3j","operator:type":"government","amenity":"school"}},{"id":40082,"type":"Feature","geometry":{"type":"Point","coordinates":[16.8764499,50.34411]},"properties":{"ref:rspo":40082,"official_name":"Przedszkole Z Oddzia\u0142ami Integracyjnymi w L\u0105dku-Zdroju","name":"Przedszkole Z Oddzia\u0142ami Integracyjnymi w L\u0105dku-Zdroju","addr:country":"PL","addr:postcode":"57-540","addr:city":"L\u0105dek-Zdr\u00f3j","addr:street":"ul. Powsta\u0144c\u00f3w Wielkopolskich","addr:housenumber":"26A","addr:teryt:simc":17377,"addr:teryt:sym_ul":984203,"contact:phone":"+48 746396099","contact:email":"gppladek@op.pl","ref:regon":"890003259","ref:vatin":"PL8811401079","operator":"Gmina L\u0105dek-Zdr\u00f3j","operator:type":"government","amenity":"kindergarten"}},{"id":40079,"type":"Feature","geometry":{"type":"Point","coordinates":[16.86887,50.34573]},"properties":{"isced:level":"1;2","ref:rspo":40079,"official_name":"Szko\u0142a Podstawowa Nr 1 im. Janusza Korczaka","name":"Szko\u0142a Podstawowa Nr 1","addr:country":"PL","addr:postcode":"57-540","addr:city":"L\u0105dek-Zdr\u00f3j","addr:street":"ul. Ko\u015bcielna","addr:housenumber":"31","addr:teryt:simc":9546,"addr:teryt:sym_ul":984203,"contact:phone":"+48 748146440","contact:email":"sekretariat@sp1ladekzdroj.pl","contact:website":"http:\/\/www.sp1ladekzdroj.pl","ref:regon":"001073389","ref:vatin":"PL8811330899","operator":"Gmina L\u0105dek-Zdr\u00f3j","operator:type":"government","amenity":"school"}},{"id":40077,"type":"Feature","geometry":{"type":"Point","coordinates":[16.77564,50.34904]},"properties":{"isced:level":"1;2","ref:rspo":40077,"official_name":"Szko\u0142a Podstawowa im. Wincentego Witosa w Trzebieszowicach","name":"Szko\u0142a Podstawowa","addr:country":"PL","addr:postcode":"57-540","addr:place":"Trzebieszowice","addr:housenumber":"150","addr:teryt:sym_ul":853211,"contact:phone":"+48 748689289","contact:email":"sptrzebieszowice@wp.pl","contact:website":"http:\/\/www.sptrzebieszowice.szkolnastrona.pl","ref:regon":"000878889","ref:vatin":"PL8811330652","operator":"Gmina L\u0105dek-Zdr\u00f3j","operator:type":"government","amenity":"school"}}]}