{
    "type": "FeatureCollection",
    "features": [
        {
            "id": 69853,
            "type": "Feature",
            "geometry": {
                "type": "Point",
                "coordinates": [
                    18.90987,
                    51.50152
                ]
            },
            "properties": {
                "isced:level": "1;2",
                "ref:rspo": 69853,
                "official_name": "Spo\u0142eczna Szko\u0142a Podstawowa w Rembieszowie",
                "name": "Spo\u0142eczna Szko\u0142a Podstawowa w Rembieszowie",
                "addr:postcode": "98-161",
                "addr:place": "Rembiesz\u00f3w",
                "addr:housenumber": "87",
                "addr:teryt:simc": 721337,
                "email": "ssprembieszow@op.pl",
                "ref:regon": "101494805",
                "ref:vatin": "PL8291689162",
                "operator": "Stowarzyszenie Inicjatyw Edukacyjnych I Spo\u0142ecznych \"Rembiesz\u00f3w\"",
                "operator:type": "ngo",
                "amenity": "school"
            }
        },
        {
            "id": 88280,
            "type": "Feature",
            "geometry": {
                "type": "Point",
                "coordinates": [
                    18.88406,
                    51.54527
                ]
            },
            "properties": {
                "isced:level": "1;2",
                "ref:rspo": 88280,
                "official_name": "Szko\u0142a Podstawowa im. 4. Pu\u0142ku Piechoty Legion\u00f3w w Zapolicach",
                "name": "Szko\u0142a Podstawowa",
                "addr:postcode": "98-161",
                "addr:city": "Zapolice",
                "addr:street": "G\u0142\u00f3wna",
                "addr:housenumber": "19",
                "addr:teryt:simc": 721515,
                "addr:teryt:sym_ul": 5635,
                "phone": "+48 438231979",
                "email": "spzapolice@poczta.onet.pl",
                "website": "https:\/\/zsozapolice.szkolnastrona.pl\/",
                "ref:regon": "000734200",
                "ref:vatin": "PL8291720802",
                "operator": "Gmina Zapolice",
                "operator:type": "government",
                "amenity": "school"
            }
        },
        {
            "id": 81047,
            "type": "Feature",
            "geometry": {
                "type": "Point",
                "coordinates": [
                    18.88333,
                    51.54579
                ]
            },
            "properties": {
                "ref:rspo": 81047,
                "official_name": "Publiczne Przedszkole w Zapolicach",
                "name": "Publiczne Przedszkole w Zapolicach",
                "addr:postcode": "98-161",
                "addr:city": "Zapolice",
                "addr:street": "G\u0142\u00f3wna",
                "addr:housenumber": "19A",
                "addr:teryt:simc": 721515,
                "addr:teryt:sym_ul": 5635,
                "phone": "+48 438231923",
                "email": "ppzapolice@op.pl",
                "website": "http:\/\/www.przedszkolezapolice.edupage.org",
                "ref:regon": "731623985",
                "ref:vatin": "PL8291520598",
                "operator": "Gmina Zapolice",
                "operator:type": "government",
                "amenity": "kindergarten"
            }
        }
    ]
}