{
    "type": "FeatureCollection",
    "features": [
        {
            "id": 90144,
            "type": "Feature",
            "geometry": {
                "type": "Point",
                "coordinates": [
                    15.67446,
                    52.31308
                ]
            },
            "properties": {
                "ref:rspo": 90144,
                "official_name": "Szkolne Schronisko M\u0142odzie\u017cowe w Pszczewie",
                "name": "Szkolne Schronisko M\u0142odzie\u017cowe w Pszczewie",
                "addr:country": "PL",
                "addr:postcode": "66-330",
                "addr:city": "Pszczew",
                "addr:street": "ul. Stra\u017cacka",
                "addr:housenumber": "1",
                "addr:teryt:simc": 21271,
                "addr:teryt:sym_ul": 186097,
                "ref:regon": "080291771",
                "operator": "Gmina Pszczew",
                "operator:type": "government",
                "tourism": "hostel"
            }
        },
        {
            "id": 82873,
            "type": "Feature",
            "geometry": {
                "type": "Point",
                "coordinates": [
                    15.7815,
                    52.47626
                ]
            },
            "properties": {
                "ref:rspo": 82873,
                "official_name": "Przedszkole Samorz\u0105dowe im. Pszcz\u00f3\u0142ki Mai w Pszczewie",
                "name": "Przedszkole Samorz\u0105dowe",
                "addr:country": "PL",
                "addr:postcode": "66-330",
                "addr:city": "Pszczew",
                "addr:street": "ul. Stefana Batorego",
                "addr:housenumber": "1a",
                "addr:teryt:simc": 891,
                "addr:teryt:sym_ul": 186097,
                "contact:phone": "+48 957492334",
                "contact:email": "przedszkole.pszczew@wp.pl",
                "contact:website": "http:\/\/www.przedszkolepszczewedupage.pl",
                "ref:regon": "211191784",
                "ref:vatin": "PL5951001390",
                "operator": "Gmina Pszczew",
                "operator:type": "government",
                "amenity": "kindergarten"
            }
        },
        {
            "id": 79940,
            "type": "Feature",
            "geometry": {
                "type": "Point",
                "coordinates": [
                    15.77567,
                    52.48412
                ]
            },
            "properties": {
                "isced:level": "1;2",
                "ref:rspo": 79940,
                "official_name": "Szko\u0142a Podstawowa im. Miko\u0142aja Kopernika w Pszczewie",
                "name": "Szko\u0142a Podstawowa",
                "addr:country": "PL",
                "addr:postcode": "66-330",
                "addr:city": "Pszczew",
                "addr:street": "ul. W\u0142adys\u0142awa Sikorskiego",
                "addr:housenumber": "23",
                "addr:teryt:simc": 19914,
                "addr:teryt:sym_ul": 186097,
                "contact:phone": "+48 957492335",
                "contact:email": "sppszczew@gmail.com",
                "contact:website": "http:\/\/www.spszczew.edupage.org",
                "ref:regon": "210313558",
                "ref:vatin": "PL5961690942",
                "operator": "Gmina Pszczew",
                "operator:type": "government",
                "amenity": "school"
            }
        }
    ]
}