{"type":"FeatureCollection","features":[{"id":278585,"type":"Feature","geometry":{"type":"Point","coordinates":[22.495189666748,50.05878829956]},"properties":{"isced:level":"1;2","ref:rspo":278585,"official_name":"Szko\u0142a Filialna w Cieplicach Szko\u0142y Podstawowej im. Jana Paw\u0142a II w Adam\u00f3wce","name":"Szko\u0142a Filialna w Cieplicach Szko\u0142y Podstawowej","addr:country":"PL","addr:postcode":"37-534","addr:place":"Cieplice","addr:housenumber":"41","addr:teryt:sym_ul":598629,"contact:phone":"+48 166229105","contact:email":"ada_szkola@wp.pl","ref:regon":"663261000","operator":"Gmina Adam\u00f3wka","operator:type":"government","amenity":"school","note":"Parent RSPO: 89023"}},{"id":89023,"type":"Feature","geometry":{"type":"Point","coordinates":[22.69529,50.25826]},"properties":{"isced:level":"1;2","ref:rspo":89023,"official_name":"Szko\u0142a Podstawowa im. Jana Paw\u0142a II w Adam\u00f3wce","name":"Szko\u0142a Podstawowa","addr:country":"PL","addr:postcode":"37-534","addr:place":"Adam\u00f3wka","addr:housenumber":"26","addr:teryt:sym_ul":598569,"contact:phone":"+48 166229105","contact:email":"ada_szkola@wp.pl","contact:website":"http:\/\/spadamowka.edupage.org\/","ref:regon":"000663261","ref:vatin":"PL7941781944","operator":"Gmina Adam\u00f3wka","operator:type":"government","amenity":"school","note":"Children RSPO: 278585"}},{"id":89026,"type":"Feature","geometry":{"type":"Point","coordinates":[22.76233,50.28558]},"properties":{"isced:level":"1;2","ref:rspo":89026,"official_name":"Szko\u0142a Podstawowa im. B\u0142. Ks. Jerzego Popie\u0142uszki w Majdanie Sieniawskim","name":"Szko\u0142a Podstawowa","addr:country":"PL","addr:postcode":"37-534","addr:place":"Majdan Sieniawski","addr:housenumber":"197","addr:teryt:sym_ul":598842,"contact:phone":"+48 166229104","contact:email":"spmajdan@o2.pl","contact:website":"http:\/\/spmajdan.cal.pl","ref:regon":"001207230","ref:vatin":"PL7941777948","operator":"Gmina Adam\u00f3wka","operator:type":"government","amenity":"school"}}]}