{
    "type": "FeatureCollection",
    "features": [
        {
            "id": 50855,
            "type": "Feature",
            "geometry": {
                "type": "Point",
                "coordinates": [
                    16.09015,
                    53.34119
                ]
            },
            "properties": {
                "ref:rspo": 50855,
                "official_name": "Przedszkole \"S\u0142oneczko\" w Miros\u0142awcu",
                "name": "Przedszkole \"S\u0142oneczko\" w Miros\u0142awcu",
                "addr:country": "PL",
                "addr:postcode": "78-650",
                "addr:city": "Miros\u0142awiec",
                "addr:street": "Zamkowa",
                "addr:housenumber": "10a",
                "addr:teryt:simc": 967038,
                "addr:teryt:sym_ul": 25547,
                "contact:phone": "+48 672595005",
                "contact:email": "sekretariat@spsmiroslawiec.pl",
                "contact:website": "http:\/\/www.przedszkolemiroslawiec.superszkolna.pl",
                "ref:regon": "320935540",
                "ref:vatin": "PL7651022555",
                "operator": "Gmina Miros\u0142awiec",
                "operator:type": "government",
                "amenity": "kindergarten"
            }
        },
        {
            "id": 68341,
            "type": "Feature",
            "geometry": {
                "type": "Point",
                "coordinates": [
                    16.08961,
                    53.34237
                ]
            },
            "properties": {
                "isced:level": "1;2",
                "ref:rspo": 68341,
                "official_name": "Szko\u0142a Podstawowa im. Lotnik\u00f3w Polskich w Miros\u0142awcu",
                "name": "Szko\u0142a Podstawowa",
                "addr:country": "PL",
                "addr:postcode": "78-650",
                "addr:city": "Miros\u0142awiec",
                "addr:street": "Wolno\u015bci",
                "addr:housenumber": "21",
                "addr:teryt:simc": 967038,
                "addr:teryt:sym_ul": 24687,
                "contact:phone": "+48 672595021",
                "contact:email": "szkola@spmiroslawiec.pl",
                "contact:website": "http:\/\/spmiroslawiec.pl",
                "ref:regon": "000596978",
                "operator": "Gmina Miros\u0142awiec",
                "operator:type": "government",
                "amenity": "school"
            }
        },
        {
            "id": 68340,
            "type": "Feature",
            "geometry": {
                "type": "Point",
                "coordinates": [
                    16.25318,
                    53.34248
                ]
            },
            "properties": {
                "isced:level": "1;2",
                "ref:rspo": 68340,
                "official_name": "Szko\u0142a Podstawowa w Piecniku",
                "name": "Szko\u0142a Podstawowa w Piecniku",
                "addr:country": "PL",
                "addr:postcode": "78-650",
                "addr:place": "Piecnik",
                "addr:housenumber": "8",
                "addr:teryt:simc": 528385,
                "contact:phone": "+48 672595108",
                "contact:email": "sekretariat@szkolapiecnik.pl",
                "contact:website": "http:\/\/szkolapiecnik.pl",
                "ref:regon": "001130437",
                "operator": "Gmina Miros\u0142awiec",
                "operator:type": "government",
                "amenity": "school"
            }
        }
    ]
}