{
    "type": "FeatureCollection",
    "features": [
        {
            "id": 23847,
            "type": "Feature",
            "geometry": {
                "type": "Point",
                "coordinates": [
                    20.37164,
                    54.31409
                ]
            },
            "properties": {
                "isced:level": "1;2",
                "ref:rspo": 23847,
                "official_name": "Szko\u0142a Podstawowa im. Janusza Korczaka w Kandytach",
                "name": "Szko\u0142a Podstawowa",
                "addr:country": "PL",
                "addr:postcode": "11-220",
                "addr:place": "Kandyty",
                "addr:housenumber": "77",
                "addr:teryt:sym_ul": 474123,
                "contact:phone": "+48 897619010",
                "contact:email": "spkandyty@wp.pl",
                "contact:website": "http:\/\/www.spkandyty.edupage.org",
                "ref:regon": "001125399",
                "operator": "Gmina G\u00f3rowo I\u0142aweckie",
                "operator:type": "government",
                "amenity": "school",
                "note": "Children RSPO: 91014;91015"
            }
        },
        {
            "id": 91014,
            "type": "Feature",
            "geometry": {
                "type": "Point",
                "coordinates": [
                    20.37164,
                    54.31406
                ]
            },
            "properties": {
                "isced:level": "1;2",
                "ref:rspo": 91014,
                "official_name": "Szko\u0142a Filialna im. Ireny Kwinto w Pieszkowie Szko\u0142a Podstawowa im. Janusza Korczaka w Kandytach",
                "name": "Szko\u0142a Filialna",
                "addr:country": "PL",
                "addr:postcode": "11-220",
                "addr:place": "Kandyty",
                "addr:housenumber": "77",
                "addr:teryt:sym_ul": 474123,
                "contact:phone": "+48 897619010",
                "contact:email": "spkandyty@wp.pl",
                "contact:website": "http:\/\/www.spkandyty.edupage.org",
                "ref:regon": "112539900",
                "operator": "Gmina G\u00f3rowo I\u0142aweckie",
                "operator:type": "government",
                "amenity": "school",
                "note": "Parent RSPO: 23847"
            }
        },
        {
            "id": 91015,
            "type": "Feature",
            "geometry": {
                "type": "Point",
                "coordinates": [
                    20.37164,
                    54.31403
                ]
            },
            "properties": {
                "isced:level": "1;2",
                "ref:rspo": 91015,
                "official_name": "Szko\u0142a Filialna im. Kornela Makuszy\u0144skiego w Toprzynach Szko\u0142a Podstawowa im. Janusza Korczaka w Kandytach",
                "name": "Szko\u0142a Filialna",
                "addr:country": "PL",
                "addr:postcode": "11-220",
                "addr:place": "Kandyty",
                "addr:housenumber": "77",
                "addr:teryt:sym_ul": 474123,
                "contact:phone": "+48 897619010",
                "contact:email": "spkandyty@wp.pl",
                "contact:website": "http:\/\/www.spkandyty.edupage.org",
                "ref:regon": "112539900",
                "operator": "Gmina G\u00f3rowo I\u0142aweckie",
                "operator:type": "government",
                "amenity": "school",
                "note": "Parent RSPO: 23847"
            }
        }
    ]
}