{
    "type": "FeatureCollection",
    "features": [
        {
            "id": 68704,
            "type": "Feature",
            "geometry": {
                "type": "Point",
                "coordinates": [
                    20.2356181,
                    50.324104
                ]
            },
            "properties": {
                "isced:level": "1;2",
                "ref:rspo": 68704,
                "official_name": "Szko\u0142a Podstawowa im. Tadeusza Ko\u015bciuszki",
                "name": "Szko\u0142a Podstawowa",
                "addr:postcode": "32-222",
                "addr:place": "Rac\u0142awice",
                "addr:housenumber": "147",
                "addr:city:simc": 264319,
                "phone": "+48 413844005",
                "email": "spraclawice@poczta.onet.pl",
                "website": "http:\/\/www.spraclawice.szkolnastrona.pl",
                "ref:regon": "000600622",
                "ref:vatin": "PL6591419589",
                "operator": "Gmina Rac\u0142awice",
                "operator:type": "government",
                "amenity": "school"
            }
        }
    ]
}