{
    "type": "FeatureCollection",
    "features": [
        {
            "id": 53900,
            "type": "Feature",
            "geometry": {
                "type": "Point",
                "coordinates": [
                    22.22854,
                    52.62589
                ]
            },
            "properties": {
                "ref:rspo": 53900,
                "official_name": "Zesp\u00f3\u0142 Szk\u00f3\u0142 w Ceranowie",
                "name": "Zesp\u00f3\u0142 Szk\u00f3\u0142 w Ceranowie",
                "addr:postcode": "08-322",
                "addr:place": "Ceran\u00f3w",
                "addr:housenumber": "206",
                "addr:city:simc": 669387,
                "phone": "+48 257870727",
                "email": "gmceranow@poczta.onet.pl",
                "website": "http:\/\/spceranow.pl",
                "ref:regon": "712548132",
                "ref:vatin": "PL8231645830",
                "operator": "Gmina Ceran\u00f3w",
                "operator:type": "government",
                "landuse": "education",
                "fixme": "amenity=school, amenity=college albo landuse=education w zale\u017cno\u015bci od tego, jakie plac\u00f3wki wchodz\u0105 w sk\u0142ad zespo\u0142u. Sprawd\u017a, kiedy stosowa\u0107 amenity=* a kiedy landuse=education.",
                "note": "Children RSPO: 109151;109308"
            }
        },
        {
            "id": 109151,
            "type": "Feature",
            "geometry": {
                "type": "Point",
                "coordinates": [
                    22.22854,
                    52.625859999999996
                ]
            },
            "properties": {
                "isced:level": "1;2",
                "ref:rspo": 109151,
                "official_name": "Publiczna Szko\u0142a Podstawowa w Ceranowie im. Ludwika G\u00f3rskiego",
                "name": "Publiczna Szko\u0142a Podstawowa w Ceranowie",
                "addr:postcode": "08-322",
                "addr:place": "Ceran\u00f3w",
                "addr:housenumber": "206",
                "addr:city:simc": 669387,
                "phone": "+48 257870727",
                "email": "gmceranow@poczta.onet.pl",
                "website": "http:\/\/spceranow.pl",
                "ref:regon": "000717979",
                "ref:vatin": "PL8231237640",
                "operator": "Gmina Ceran\u00f3w",
                "operator:type": "government",
                "amenity": "school",
                "note": "Parent RSPO: 53900"
            }
        },
        {
            "id": 109308,
            "type": "Feature",
            "geometry": {
                "type": "Point",
                "coordinates": [
                    22.22378,
                    52.62798
                ]
            },
            "properties": {
                "ref:rspo": 109308,
                "official_name": "Gminne Przedszkole w Ceranowie",
                "name": "Gminne Przedszkole w Ceranowie",
                "addr:postcode": "08-322",
                "addr:place": "Ceran\u00f3w",
                "addr:housenumber": "23",
                "addr:city:simc": 669387,
                "phone": "+48 257870817",
                "email": "gpceranow@wp.pl",
                "website": "http:\/\/spceranow.pl",
                "ref:regon": "712544418",
                "ref:vatin": "PL8231635613",
                "operator": "Gmina Ceran\u00f3w",
                "operator:type": "government",
                "amenity": "kindergarten",
                "note": "Parent RSPO: 53900"
            }
        }
    ]
}