{
    "type": "FeatureCollection",
    "features": [
        {
            "id": 43514,
            "type": "Feature",
            "geometry": {
                "type": "Point",
                "coordinates": [
                    16.215004,
                    54.052034
                ]
            },
            "properties": {
                "isced:level": "1;2",
                "ref:rspo": 43514,
                "official_name": "Szko\u0142a Podstawowa w Zegrzu Pomorskim",
                "name": "Szko\u0142a Podstawowa w Zegrzu Pomorskim",
                "addr:postcode": "76-024",
                "addr:place": "Zegrze Pomorskie",
                "addr:housenumber": "32A",
                "addr:city:simc": 313437,
                "phone": "+48 943183128",
                "email": "szkola@spzegrzepom.pl",
                "website": "http:\/\/spzegrzepom.pl",
                "ref:regon": "001176669",
                "ref:vatin": "PL4990647569",
                "operator": "Gmina \u015awieszyno",
                "operator:type": "government",
                "amenity": "school"
            }
        },
        {
            "id": 43515,
            "type": "Feature",
            "geometry": {
                "type": "Point",
                "coordinates": [
                    16.169656,
                    54.121347
                ]
            },
            "properties": {
                "ref:rspo": 43515,
                "official_name": "Przedszkole Gminne w \u015awieszynie",
                "name": "Przedszkole Gminne w \u015awieszynie",
                "addr:postcode": "76-024",
                "addr:place": "\u015awieszyno",
                "addr:housenumber": "45A",
                "addr:city:simc": 313331,
                "phone": "+48 943161221",
                "email": "przedszkole.swieszyno@neostrada.pl",
                "website": "http:\/\/www.przedszkole-swieszyno.neostrada.pl",
                "ref:regon": "330461530",
                "ref:vatin": "PL4990647575",
                "operator": "Gmina \u015awieszyno",
                "operator:type": "government",
                "amenity": "kindergarten"
            }
        },
        {
            "id": 133796,
            "type": "Feature",
            "geometry": {
                "type": "Point",
                "coordinates": [
                    16.1675299,
                    54.1236019
                ]
            },
            "properties": {
                "isced:level": "1;2",
                "ref:rspo": 133796,
                "official_name": "Szko\u0142a Podstawowa Imienia 27 Wo\u0142y\u0144skiej Dywizji Piechoty Armii Krajowej w \u015awieszynie",
                "name": "Szko\u0142a Podstawowa Imienia 27 Wo\u0142y\u0144skiej Dywizji Piechoty Armii Krajowej w \u015awieszynie",
                "addr:postcode": "76-024",
                "addr:place": "\u015awieszyno",
                "addr:housenumber": "6",
                "addr:city:simc": 313331,
                "phone": "+48 943161225",
                "email": "szkola@spswieszyno.pl",
                "website": "http:\/\/spswieszyno.pl",
                "ref:regon": "367671419",
                "ref:vatin": "PL4990667052",
                "operator": "Gmina \u015awieszyno",
                "operator:type": "government",
                "amenity": "school"
            }
        },
        {
            "id": 43513,
            "type": "Feature",
            "geometry": {
                "type": "Point",
                "coordinates": [
                    16.180277,
                    54.152357
                ]
            },
            "properties": {
                "isced:level": "1;2",
                "ref:rspo": 43513,
                "official_name": "Szko\u0142a Podstawowa im. Wis\u0142awy Szymborskiej w Konikowie",
                "name": "Szko\u0142a Podstawowa",
                "addr:postcode": "76-024",
                "addr:place": "Konikowo",
                "addr:housenumber": "47",
                "addr:city:simc": 313220,
                "phone": "+48 943161222",
                "email": "sp_konikowo@wp.pl",
                "website": "http:\/\/www.sp-konikowo.edu.pl",
                "ref:regon": "331006207",
                "ref:vatin": "PL4990647581",
                "operator": "Gmina \u015awieszyno",
                "operator:type": "government",
                "amenity": "school"
            }
        }
    ]
}