{"type":"FeatureCollection","features":[{"id":41105,"type":"Feature","geometry":{"type":"Point","coordinates":[19.70727,51.75741]},"properties":{"isced:level":"1;2","ref:rspo":41105,"official_name":"Szko\u0142a Podstawowa w Ga\u0142k\u00f3wku-Kolonii","name":"Szko\u0142a Podstawowa w Ga\u0142k\u00f3wku-Kolonii","addr:country":"PL","addr:postcode":"95-060","addr:place":"Ga\u0142k\u00f3wek-Kolonia","addr:housenumber":"38","addr:teryt:sym_ul":725520,"contact:phone":"+48 468742760","contact:email":"spgalkol@wp.pl","contact:website":"http:\/\/www.spgalkol.szkoly.lodz.pl","ref:regon":"001122946","ref:vatin":"PL8331320978","operator":"Gmina Brzeziny","operator:type":"government","amenity":"school"}},{"id":41107,"type":"Feature","geometry":{"type":"Point","coordinates":[19.77261,51.76849]},"properties":{"isced:level":"1;2","ref:rspo":41107,"official_name":"Szko\u0142a Podstawowa w Bogdance","name":"Szko\u0142a Podstawowa w Bogdance","addr:country":"PL","addr:postcode":"95-060","addr:place":"Bogdanka","addr:housenumber":"5","addr:teryt:sym_ul":725878,"contact:phone":"+48 468743281","contact:email":"spbogdanka@poczta.fm","contact:website":"http:\/\/www.edupage.org","ref:regon":"001122952","ref:vatin":"PL8331320961","operator":"Gmina Brzeziny","operator:type":"government","amenity":"school"}},{"id":41106,"type":"Feature","geometry":{"type":"Point","coordinates":[19.72803,51.85193]},"properties":{"isced:level":"1;2","ref:rspo":41106,"official_name":"Szko\u0142a Podstawowa w D\u0105br\u00f3wce Du\u017cej","name":"Szko\u0142a Podstawowa w D\u0105br\u00f3wce Du\u017cej","addr:country":"PL","addr:postcode":"95-060","addr:place":"D\u0105br\u00f3wka Du\u017ca","addr:housenumber":"60","addr:teryt:sym_ul":725482,"contact:phone":"+48 468742785","contact:email":"szkola.dd@wp.pl","contact:website":"http:\/\/szkola.dd.superszkolna.pl","ref:regon":"001122923","ref:vatin":"PL8331319975","operator":"Gmina Brzeziny","operator:type":"government","amenity":"school"}}]}