{
    "type": "FeatureCollection",
    "features": [
        {
            "id": 267596,
            "type": "Feature",
            "geometry": {
                "type": "Point",
                "coordinates": [
                    18.62606,
                    52.56356
                ]
            },
            "properties": {
                "ref:rspo": 267596,
                "official_name": "Zesp\u00f3\u0142 Szkolno-Przedszkolny",
                "name": "Zesp\u00f3\u0142 Szkolno-Przedszkolny",
                "addr:country": "PL",
                "addr:postcode": "88-231",
                "addr:place": "Morzyce",
                "addr:housenumber": "27",
                "addr:teryt:sym_ul": 859969,
                "contact:phone": "+48 542851319",
                "ref:regon": "380370662",
                "operator": "Gmina Byto\u0144",
                "operator:type": "government",
                "landuse": "education",
                "fixme": "amenity=school, amenity=college albo landuse=education w zale\u017cno\u015bci od tego, jakie plac\u00f3wki wchodz\u0105 w sk\u0142ad zespo\u0142u. Sprawd\u017a, kiedy stosowa\u0107 amenity=* a kiedy landuse=education.",
                "note": "Children RSPO: 74680;267283"
            }
        },
        {
            "id": 74680,
            "type": "Feature",
            "geometry": {
                "type": "Point",
                "coordinates": [
                    18.62606,
                    52.56353
                ]
            },
            "properties": {
                "isced:level": "1;2",
                "ref:rspo": 74680,
                "official_name": "Szko\u0142a Podstawowa Morzyce 27 88-231 Byto\u0144",
                "name": "Szko\u0142a Podstawowa Morzyce 27 88-231 Byto\u0144",
                "addr:country": "PL",
                "addr:postcode": "88-231",
                "addr:place": "Morzyce",
                "addr:housenumber": "27",
                "addr:door": "27",
                "addr:teryt:sym_ul": 859981,
                "contact:phone": "+48 542851319",
                "contact:email": "spmorzyce@poczta.onet.pl",
                "contact:website": "http:\/\/www.spmorzyce.szkolnastrona.pl",
                "ref:regon": "000994868",
                "ref:vatin": "PL8891032499",
                "operator": "Gmina Byto\u0144",
                "operator:type": "government",
                "amenity": "school",
                "note": "Parent RSPO: 267596"
            }
        },
        {
            "id": 267283,
            "type": "Feature",
            "geometry": {
                "type": "Point",
                "coordinates": [
                    18.62606,
                    52.563500000000005
                ]
            },
            "properties": {
                "ref:rspo": 267283,
                "official_name": "Publiczne Przedszkole",
                "name": "Publiczne Przedszkole",
                "addr:country": "PL",
                "addr:postcode": "88-231",
                "addr:place": "Morzyce",
                "addr:housenumber": "27",
                "addr:door": "27",
                "addr:teryt:sym_ul": 859969,
                "contact:phone": "+48 542851319",
                "ref:regon": "380058321",
                "operator": "Gmina Byto\u0144",
                "operator:type": "government",
                "amenity": "kindergarten",
                "note": "Parent RSPO: 267596"
            }
        }
    ]
}