{
    "type": "FeatureCollection",
    "features": [
        {
            "id": 119096,
            "type": "Feature",
            "geometry": {
                "type": "Point",
                "coordinates": [
                    19.01593,
                    54.13336
                ]
            },
            "properties": {
                "ref:rspo": 119096,
                "official_name": "Zesp\u00f3\u0142 Szkolno-Przedszkolny w Nowym Stawie",
                "name": "Zesp\u00f3\u0142 Szkolno-Przedszkolny w Nowym Stawie",
                "addr:postcode": "82-230",
                "addr:city": "Nowy Staw",
                "addr:street": "Bankowa",
                "addr:housenumber": "2",
                "addr:city:simc": 932904,
                "addr:street:sym_ul": 692,
                "phone": "+48 552715144",
                "email": "sekretariat@zspnowystaw.pl",
                "website": "http:\/\/www.spnowystaw.pl",
                "ref:regon": "221942857",
                "ref:vatin": "PL5792251920",
                "operator": "Gmina Nowy Staw",
                "operator:type": "government",
                "landuse": "education",
                "fixme": "amenity=school, amenity=college albo landuse=education w zale\u017cno\u015bci od tego, jakie plac\u00f3wki wchodz\u0105 w sk\u0142ad zespo\u0142u. Sprawd\u017a, kiedy stosowa\u0107 amenity=* a kiedy landuse=education.",
                "note": "Children RSPO: 34880;34886"
            }
        },
        {
            "id": 34880,
            "type": "Feature",
            "geometry": {
                "type": "Point",
                "coordinates": [
                    19.00288,
                    54.13559
                ]
            },
            "properties": {
                "isced:level": "1;2",
                "ref:rspo": 34880,
                "official_name": "Szko\u0142a Podstawowa nr 2 im. Wincentego Pola\nW Nowym Stawie",
                "name": "Szko\u0142a Podstawowa nr 2",
                "addr:postcode": "82-230",
                "addr:city": "Nowy Staw",
                "addr:street": "Gda\u0144ska",
                "addr:housenumber": "53",
                "addr:city:simc": 932904,
                "addr:street:sym_ul": 5431,
                "phone": "+48 552715640",
                "email": "spnowystaw@poczta.onet.pl",
                "ref:regon": "000677731",
                "ref:vatin": "PL5791617856",
                "operator": "Gmina Nowy Staw",
                "operator:type": "government",
                "amenity": "school",
                "note": "Parent RSPO: 119096"
            }
        },
        {
            "id": 34886,
            "type": "Feature",
            "geometry": {
                "type": "Point",
                "coordinates": [
                    19.00442,
                    54.13612
                ]
            },
            "properties": {
                "ref:rspo": 34886,
                "official_name": "Przedszkole w Nowym Stawie",
                "name": "Przedszkole w Nowym Stawie",
                "addr:postcode": "82-230",
                "addr:city": "Nowy Staw",
                "addr:street": "Gda\u0144ska",
                "addr:housenumber": "43B",
                "addr:city:simc": 932904,
                "addr:street:sym_ul": 5431,
                "phone": "+48 552715240",
                "email": "przedszkolens@wp.pl",
                "website": "http:\/\/www.przedszkolenowystaw.szkolna.net",
                "ref:regon": "170001312",
                "ref:vatin": "PL5791617879",
                "operator": "Gmina Nowy Staw",
                "operator:type": "government",
                "amenity": "kindergarten",
                "note": "Parent RSPO: 119096"
            }
        }
    ]
}