{"type":"FeatureCollection","features":[{"id":107331,"type":"Feature","geometry":{"type":"Point","coordinates":[22.9318182,51.0553535]},"properties":{"isced:level":"1;2","ref:rspo":107331,"official_name":"Szko\u0142a Podstawowa Imienia B\u0142ogos\u0142awionego Jana Paw\u0142a II w Siedliskach Drugich","name":"Szko\u0142a Podstawowa Imienia B\u0142ogos\u0142awionego Jana Paw\u0142a II w Siedliskach Drugich","addr:country":"PL","addr:postcode":"21-060","addr:place":"Siedliska Drugie","addr:housenumber":"190","addr:teryt:sym_ul":380451,"contact:phone":"+48 815853130","contact:email":"spsiedliska@wp.pl","contact:website":"http:\/\/www.sp-siedliska.pl","ref:regon":"001177019","ref:vatin":"PL5641663843","operator":"Gmina Fajs\u0142awice","operator:type":"government","amenity":"school"}},{"id":105653,"type":"Feature","geometry":{"type":"Point","coordinates":[22.96824,51.09669]},"properties":{"isced:level":"1;2","ref:rspo":105653,"official_name":"Szko\u0142a Podstawowa Imienia Powsta\u0144c\u00f3w Styczniowych w Fajs\u0142awicach","name":"Szko\u0142a Podstawowa Imienia Powsta\u0144c\u00f3w Styczniowych w Fajs\u0142awicach","addr:country":"PL","addr:postcode":"21-060","addr:place":"Fajs\u0142awice","addr:housenumber":"130A","addr:teryt:sym_ul":380391,"contact:phone":"+48 815853025","contact:email":"sp@sp.fajslawice.eu","contact:website":"http:\/\/www.sp-fajslawice.pl","ref:regon":"001238790","ref:vatin":"PL7131406999","operator":"Gmina Fajs\u0142awice","operator:type":"government","amenity":"school"}}]}