{
    "type": "FeatureCollection",
    "features": [
        {
            "id": 130763,
            "type": "Feature",
            "geometry": {
                "type": "Point",
                "coordinates": [
                    20.68329,
                    49.48078
                ]
            },
            "properties": {
                "ref:rspo": 130763,
                "official_name": "Prywatne Przedszkole \"Bajeczny Ogr\u00f3dek\"",
                "name": "Prywatne Przedszkole \"Bajeczny Ogr\u00f3dek\"",
                "addr:postcode": "33-343",
                "addr:place": "Sucha Struga",
                "addr:housenumber": "211",
                "addr:teryt:simc": 459721,
                "phone": "+48 515268797",
                "ref:regon": "364486360",
                "ref:vatin": "PL7352384078",
                "operator": "Marzena Kruczek",
                "operator:type": "private",
                "amenity": "kindergarten"
            }
        },
        {
            "id": 10340,
            "type": "Feature",
            "geometry": {
                "type": "Point",
                "coordinates": [
                    20.67676,
                    49.4898499
                ]
            },
            "properties": {
                "ref:rspo": 10340,
                "official_name": "Dom Wczas\u00f3w Dzieci\u0119cych w Rytrze",
                "name": "Dom Wczas\u00f3w Dzieci\u0119cych w Rytrze",
                "addr:postcode": "33-343",
                "addr:place": "Rytro",
                "addr:housenumber": "99",
                "addr:teryt:simc": 459550,
                "phone": "+48 517622554",
                "email": "dwdrytro@onet.pl",
                "website": "http:\/\/dwdrytro.pl",
                "ref:regon": "122651480",
                "operator": "Stowarzyszenie Edukacji Ekologicznej I Turystycznej \"Roga\u015b\" W Rytrze",
                "operator:type": "ngo",
                "leisure": "resort"
            }
        },
        {
            "id": 77949,
            "type": "Feature",
            "geometry": {
                "type": "Point",
                "coordinates": [
                    20.66958,
                    49.49007
                ]
            },
            "properties": {
                "isced:level": "1;2",
                "ref:rspo": 77949,
                "official_name": "Szko\u0142a Podstawowa im. Stefana Pawlika w Rytrze",
                "name": "Szko\u0142a Podstawowa",
                "addr:postcode": "33-343",
                "addr:place": "Rytro",
                "addr:housenumber": "8",
                "addr:teryt:simc": 459550,
                "phone": "+48 184469005",
                "email": "rytrosp@op.pl",
                "website": "http:\/\/www.sprytro.nstrefa.pl",
                "ref:regon": "490675132",
                "ref:vatin": "PL7341518687",
                "operator": "Gmina Rytro",
                "operator:type": "government",
                "amenity": "school"
            }
        },
        {
            "id": 77950,
            "type": "Feature",
            "geometry": {
                "type": "Point",
                "coordinates": [
                    20.66958,
                    49.49004
                ]
            },
            "properties": {
                "ref:rspo": 77950,
                "official_name": "Gminne Przedszkole w Rytrze",
                "name": "Gminne Przedszkole w Rytrze",
                "addr:postcode": "33-343",
                "addr:place": "Rytro",
                "addr:housenumber": "8",
                "addr:teryt:simc": 459550,
                "phone": "+48 184469009",
                "email": "przedsz@op.pl",
                "website": "http:\/\/www.przedszkole.rytro.dlaprzedszkoli.eu",
                "ref:regon": "491900594",
                "ref:vatin": "PL7342634740",
                "operator": "Gmina Rytro",
                "operator:type": "government",
                "amenity": "kindergarten"
            }
        }
    ]
}