{
    "type": "FeatureCollection",
    "features": [
        {
            "id": 84774,
            "type": "Feature",
            "geometry": {
                "type": "Point",
                "coordinates": [
                    19.79776,
                    51.18714
                ]
            },
            "properties": {
                "isced:level": "1;2",
                "ref:rspo": 84774,
                "official_name": "Szko\u0142a Podstawowa im.marii Konopnickiej w \u0141\u0119kach Szlacheckich",
                "name": "Szko\u0142a Podstawowa im.marii Konopnickiej w \u0141\u0119kach Szlacheckich",
                "addr:country": "PL",
                "addr:postcode": "97-352",
                "addr:place": "\u0141\u0119ki Szlacheckie",
                "addr:housenumber": "60",
                "addr:teryt:simc": 545254,
                "contact:phone": "+48 447875306",
                "contact:email": "splekiszlach@interia.pl",
                "ref:regon": "001251098",
                "ref:vatin": "PL7712515187",
                "operator": "Gmina \u0141\u0119ki Szlacheckie",
                "operator:type": "government",
                "amenity": "school"
            }
        },
        {
            "id": 84858,
            "type": "Feature",
            "geometry": {
                "type": "Point",
                "coordinates": [
                    19.79776,
                    51.18711
                ]
            },
            "properties": {
                "ref:rspo": 84858,
                "official_name": "Punkt Przedszkolny w Szkole Podstawowej im. Marii Konopnickiej w \u0141\u0119kach Szlacheckich",
                "name": "Punkt Przedszkolny w Szkole Podstawowej",
                "addr:country": "PL",
                "addr:postcode": "97-352",
                "addr:place": "\u0141\u0119ki Szlacheckie",
                "addr:housenumber": "60",
                "addr:teryt:simc": 545254,
                "contact:phone": "+48 447875306",
                "contact:email": "splekiszlach@interia.pl",
                "ref:regon": "101500173",
                "operator": "Gmina \u0141\u0119ki Szlacheckie",
                "operator:type": "government",
                "amenity": "kindergarten"
            }
        },
        {
            "id": 275530,
            "type": "Feature",
            "geometry": {
                "type": "Point",
                "coordinates": [
                    19.71948,
                    51.19281
                ]
            },
            "properties": {
                "ref:rspo": 275530,
                "official_name": "Przedszkole ,, Chatka Puchatka\" w Trzepnicy",
                "name": "Przedszkole ,, Chatka Puchatka\" w Trzepnicy",
                "addr:country": "PL",
                "addr:postcode": "97-352",
                "addr:place": "Trzepnica-Kolonia",
                "addr:housenumber": "7A",
                "addr:teryt:simc": 545567,
                "contact:phone": "+48 572570010",
                "contact:email": "chatkipuchatka@gmail.com",
                "contact:website": "http:\/\/www.chatkapuchatka.info.pl",
                "ref:regon": "386924914",
                "operator": "Bo\u017cena Grobelniak",
                "operator:type": "private",
                "amenity": "kindergarten"
            }
        },
        {
            "id": 84809,
            "type": "Feature",
            "geometry": {
                "type": "Point",
                "coordinates": [
                    19.72788,
                    51.20852
                ]
            },
            "properties": {
                "isced:level": "1;2",
                "ref:rspo": 84809,
                "official_name": "Szko\u0142a Podstawowa im.andrzeja Frycza Modrzewskiego w Trzepnicy",
                "name": "Szko\u0142a Podstawowa im.andrzeja Frycza Modrzewskiego w Trzepnicy",
                "addr:country": "PL",
                "addr:postcode": "97-352",
                "addr:place": "Trzepnica-Kolonia",
                "addr:housenumber": "13A",
                "addr:teryt:simc": 545567,
                "contact:phone": "+48 447875335",
                "contact:email": "sptrzepnica@o2.pl",
                "contact:website": "http:\/\/www.sptrzepnica.szkolnastrona.pl",
                "ref:regon": "001160912",
                "ref:vatin": "PL7712515193",
                "operator": "Gmina \u0141\u0119ki Szlacheckie",
                "operator:type": "government",
                "amenity": "school"
            }
        }
    ]
}