{
    "type": "FeatureCollection",
    "features": [
        {
            "id": 42303,
            "type": "Feature",
            "geometry": {
                "type": "Point",
                "coordinates": [
                    20.4013019,
                    50.5578999
                ]
            },
            "properties": {
                "isced:level": "1;2",
                "ref:rspo": 42303,
                "official_name": "Samorz\u0105dowa Szko\u0142a Podstawowa w Mierzwinie",
                "name": "Samorz\u0105dowa Szko\u0142a Podstawowa w Mierzwinie",
                "addr:country": "PL",
                "addr:postcode": "28-313",
                "addr:place": "Mierzwin",
                "addr:housenumber": "11",
                "addr:teryt:sym_ul": 239681,
                "contact:phone": "+48 413852104",
                "contact:email": "ssp-mierzwin@wp.pl",
                "ref:regon": "001215777",
                "ref:vatin": "PL6562047636",
                "operator": "Gmina Imielno",
                "operator:type": "government",
                "amenity": "school"
            }
        },
        {
            "id": 90901,
            "type": "Feature",
            "geometry": {
                "type": "Point",
                "coordinates": [
                    20.470634,
                    50.585228
                ]
            },
            "properties": {
                "ref:rspo": 90901,
                "official_name": "Punkt Przedszkolny w Samorz\u0105dowej Szkole Podstawowej w Imielnie Z Siedzib\u0105 w Stawach",
                "name": "Punkt Przedszkolny w Samorz\u0105dowej Szkole Podstawowej w Imielnie Z Siedzib\u0105 w Stawach",
                "addr:country": "PL",
                "addr:postcode": "28-313",
                "addr:place": "Stawy",
                "addr:housenumber": "2B",
                "addr:teryt:sym_ul": 239853,
                "contact:phone": "+48 413811111",
                "contact:email": "sspimielno@o2.pl",
                "ref:regon": "260651492",
                "operator": "Gmina Imielno",
                "operator:type": "government",
                "amenity": "kindergarten"
            }
        },
        {
            "id": 22699,
            "type": "Feature",
            "geometry": {
                "type": "Point",
                "coordinates": [
                    20.48757,
                    50.60051
                ]
            },
            "properties": {
                "isced:level": "1;2",
                "ref:rspo": 22699,
                "official_name": "Samorz\u0105dowa Szko\u0142a Podstawowa w Imielnie",
                "name": "Samorz\u0105dowa Szko\u0142a Podstawowa w Imielnie",
                "addr:country": "PL",
                "addr:postcode": "28-313",
                "addr:city": "Imielno",
                "addr:street": "Ko\u015bcielna",
                "addr:housenumber": "3",
                "addr:teryt:simc": 9546,
                "addr:teryt:sym_ul": 239586,
                "contact:phone": "+48 413851224",
                "contact:email": "sspimielno@o2.pl",
                "ref:regon": "000572305",
                "ref:vatin": "PL6562047613",
                "operator": "Gmina Imielno",
                "operator:type": "government",
                "amenity": "school"
            }
        },
        {
            "id": 42300,
            "type": "Feature",
            "geometry": {
                "type": "Point",
                "coordinates": [
                    20.48935,
                    50.60505
                ]
            },
            "properties": {
                "isced:level": "1;2",
                "ref:rspo": 42300,
                "official_name": "Samorz\u0105dowa Szko\u0142a Podstawowa w Motkowicach",
                "name": "Samorz\u0105dowa Szko\u0142a Podstawowa w Motkowicach",
                "addr:country": "PL",
                "addr:postcode": "28-313",
                "addr:city": "Motkowice",
                "addr:street": "Szkolna",
                "addr:housenumber": "2",
                "addr:teryt:simc": 21970,
                "addr:teryt:sym_ul": 239698,
                "contact:phone": "+48 413851302",
                "contact:email": "szkolamotkowice@op.pl",
                "ref:regon": "001215760",
                "ref:vatin": "PL6562047607",
                "operator": "Gmina Imielno",
                "operator:type": "government",
                "amenity": "school"
            }
        }
    ]
}