{
    "type": "FeatureCollection",
    "features": [
        {
            "id": 58825,
            "type": "Feature",
            "geometry": {
                "type": "Point",
                "coordinates": [
                    16.53109,
                    52.70678
                ]
            },
            "properties": {
                "ref:rspo": 58825,
                "official_name": "Zesp\u00f3\u0142 Szk\u00f3\u0142 w Mie\u015bcie Obrzycko",
                "name": "Zesp\u00f3\u0142 Szk\u00f3\u0142 w Mie\u015bcie Obrzycko",
                "addr:postcode": "64-520",
                "addr:city": "Obrzycko",
                "addr:street": "Plac Lipowy",
                "addr:housenumber": "12",
                "addr:teryt:simc": 971212,
                "addr:teryt:sym_ul": 11149,
                "phone": "+48 612913129",
                "email": "sekretariat@zsobrzycko.pl",
                "website": "http:\/\/www.zsobrzycko.pl",
                "ref:regon": "639640472",
                "ref:vatin": "PL7871840847",
                "operator": "Miasto Obrzycko",
                "operator:type": "government",
                "landuse": "education",
                "fixme": "amenity=school, amenity=college albo landuse=education w zale\u017cno\u015bci od tego, jakie plac\u00f3wki wchodz\u0105 w sk\u0142ad zespo\u0142u. Sprawd\u017a, kiedy stosowa\u0107 amenity=* a kiedy landuse=education.",
                "note": "Children RSPO: 113890;113891"
            }
        },
        {
            "id": 113890,
            "type": "Feature",
            "geometry": {
                "type": "Point",
                "coordinates": [
                    16.53109,
                    52.70675
                ]
            },
            "properties": {
                "isced:level": "1;2",
                "ref:rspo": 113890,
                "official_name": "Szko\u0142a Podstawowa im. Powsta\u0144c\u00f3w Wielkopolskich w Obrzycku",
                "name": "Szko\u0142a Podstawowa",
                "addr:postcode": "64-520",
                "addr:city": "Obrzycko",
                "addr:street": "Plac Lipowy",
                "addr:housenumber": "12",
                "addr:teryt:simc": 971212,
                "addr:teryt:sym_ul": 11149,
                "phone": "+48 612913129",
                "email": "sekretariat@zsobrzycko.pl",
                "website": "http:\/\/www.zsobrzycko.pl",
                "ref:regon": "634236476",
                "ref:vatin": "PL7871840847",
                "operator": "Miasto Obrzycko",
                "operator:type": "government",
                "amenity": "school",
                "note": "Parent RSPO: 58825"
            }
        },
        {
            "id": 113891,
            "type": "Feature",
            "geometry": {
                "type": "Point",
                "coordinates": [
                    16.53109,
                    52.706720000000004
                ]
            },
            "properties": {
                "ref:rspo": 113891,
                "official_name": "Przedszkole Miejskie w Obrzycku \"Bajkowa Kraina\"",
                "name": "Przedszkole Miejskie w Obrzycku \"Bajkowa Kraina\"",
                "addr:postcode": "64-520",
                "addr:city": "Obrzycko",
                "addr:street": "Plac Lipowy",
                "addr:housenumber": "12",
                "addr:teryt:simc": 971212,
                "addr:teryt:sym_ul": 11149,
                "phone": "+48 612913129",
                "email": "dyrektor@zsobrzycko.pl",
                "ref:regon": "631579483",
                "ref:vatin": "PL7871840847",
                "operator": "Miasto Obrzycko",
                "operator:type": "government",
                "amenity": "kindergarten",
                "note": "Parent RSPO: 58825"
            }
        }
    ]
}