{
    "type": "FeatureCollection",
    "features": [
        {
            "id": 4244,
            "type": "Feature",
            "geometry": {
                "type": "Point",
                "coordinates": [
                    19.03494,
                    52.7349
                ]
            },
            "properties": {
                "ref:rspo": 4244,
                "official_name": "Niepubliczne Przedszkole \"Ma\u0142e Przedszkole\" w Rachcinie",
                "name": "Niepubliczne Przedszkole \"Ma\u0142e Przedszkole\" w Rachcinie",
                "addr:country": "PL",
                "addr:postcode": "87-617",
                "addr:place": "Rachcin",
                "addr:housenumber": "8A",
                "addr:teryt:sym_ul": 858579,
                "contact:phone": "+48 791400411",
                "contact:email": "przedszkolerachcin@op.pl",
                "ref:regon": "341315515",
                "operator": "Stowarzyszenie Rozwoju So\u0142ectwa Rachcin",
                "operator:type": "ngo",
                "amenity": "kindergarten"
            }
        },
        {
            "id": 4003,
            "type": "Feature",
            "geometry": {
                "type": "Point",
                "coordinates": [
                    18.95261,
                    52.78019
                ]
            },
            "properties": {
                "ref:rspo": 4003,
                "official_name": "Przedszkole Samorz\u0105dowe w Bobrownikach",
                "name": "Przedszkole Samorz\u0105dowe w Bobrownikach",
                "addr:country": "PL",
                "addr:postcode": "87-617",
                "addr:city": "Bobrowniki",
                "addr:street": "Ko\u015bcielna",
                "addr:housenumber": "5",
                "addr:teryt:simc": 9546,
                "addr:teryt:sym_ul": 858480,
                "contact:phone": "+48 542514794",
                "contact:email": "przedszkolesamorzadowebobrowniki@wp.pl",
                "ref:regon": "910004568",
                "ref:vatin": "PL4660395395",
                "operator": "Gmina Bobrowniki",
                "operator:type": "government",
                "amenity": "kindergarten"
            }
        },
        {
            "id": 3680,
            "type": "Feature",
            "geometry": {
                "type": "Point",
                "coordinates": [
                    18.95194,
                    52.78606
                ]
            },
            "properties": {
                "isced:level": "1;2",
                "ref:rspo": 3680,
                "official_name": "Szko\u0142a Podstawowa im. Karola Wojty\u0142y w Bobrownikach",
                "name": "Szko\u0142a Podstawowa",
                "addr:country": "PL",
                "addr:postcode": "87-617",
                "addr:city": "Bobrowniki",
                "addr:street": "Wyzwolenia",
                "addr:housenumber": "16",
                "addr:teryt:simc": 25133,
                "addr:teryt:sym_ul": 858480,
                "contact:phone": "+48 542514887",
                "contact:email": "spbobrowniki@o2.pl",
                "contact:website": "http:\/\/www.spbobrowniki.superszkolna.pl",
                "ref:regon": "000994839",
                "ref:vatin": "PL4660230837",
                "operator": "Gmina Bobrowniki",
                "operator:type": "government",
                "amenity": "school"
            }
        }
    ]
}