{
    "type": "FeatureCollection",
    "features": [
        {
            "id": 5104,
            "type": "Feature",
            "geometry": {
                "type": "Point",
                "coordinates": [
                    18.99908,
                    52.9949
                ]
            },
            "properties": {
                "isced:level": "1;2",
                "ref:rspo": 5104,
                "official_name": "Szko\u0142a Podstawowa im. Bohater\u00f3w Wrze\u015bnia 1939 w \u015awi\u0119tos\u0142awiu",
                "name": "Szko\u0142a Podstawowa",
                "addr:country": "PL",
                "addr:postcode": "87-408",
                "addr:place": "\u015awi\u0119tos\u0142aw",
                "addr:housenumber": "36",
                "addr:teryt:simc": 842532,
                "contact:phone": "+48 566837020",
                "contact:email": "swietoslaw32@wp.pl",
                "contact:website": "http:\/\/wwwspswietoslaw.republika.pl",
                "ref:regon": "001211087",
                "ref:vatin": "PL8781610475",
                "operator": "Gmina Ciechocin",
                "operator:type": "government",
                "amenity": "school"
            }
        },
        {
            "id": 5086,
            "type": "Feature",
            "geometry": {
                "type": "Point",
                "coordinates": [
                    18.92419,
                    53.05551
                ]
            },
            "properties": {
                "isced:level": "1;2",
                "ref:rspo": 5086,
                "official_name": "Szko\u0142a Podstawowa im. Oskara Kolberga w Ciechocinie",
                "name": "Szko\u0142a Podstawowa",
                "addr:country": "PL",
                "addr:postcode": "87-408",
                "addr:place": "Ciechocin",
                "addr:housenumber": "167",
                "addr:teryt:simc": 842271,
                "contact:phone": "+48 566837787",
                "contact:email": "spciech@interia.pl",
                "contact:website": "http:\/\/www.spciechocin.republika.pl",
                "ref:regon": "000265218",
                "ref:vatin": "PL8781066942",
                "operator": "Gmina Ciechocin",
                "operator:type": "government",
                "amenity": "school"
            }
        }
    ]
}