{
    "type": "FeatureCollection",
    "features": [
        {
            "id": 91501,
            "type": "Feature",
            "geometry": {
                "type": "Point",
                "coordinates": [
                    22.5098999,
                    53.01609
                ]
            },
            "properties": {
                "ref:rspo": 91501,
                "official_name": "Punkt Przedszkolny w Kuleszach Ko\u015bcielnych",
                "name": "Punkt Przedszkolny w Kuleszach Ko\u015bcielnych",
                "addr:country": "PL",
                "addr:postcode": "18-208",
                "addr:city": "Kulesze Ko\u015bcielne",
                "addr:street": "G\u0142\u00f3wna",
                "addr:housenumber": "2a",
                "addr:teryt:simc": 400372,
                "addr:teryt:sym_ul": 5635,
                "contact:phone": "+48 862744076",
                "contact:email": "joszkol@wp.pl",
                "contact:website": "http:\/\/www.zskulesze.szkolnastrona.pl",
                "ref:regon": "200745722",
                "operator": "Gmina Kulesze Ko\u015bcielne",
                "operator:type": "government",
                "amenity": "kindergarten"
            }
        },
        {
            "id": 103960,
            "type": "Feature",
            "geometry": {
                "type": "Point",
                "coordinates": [
                    22.5098999,
                    53.016059999999996
                ]
            },
            "properties": {
                "isced:level": "1;2",
                "ref:rspo": 103960,
                "official_name": "Szko\u0142a Podstawowa w Kuleszach Ko\u015bcielnych Imieniem Kardyna\u0142a Stefana Wyszy\u0144skiego",
                "name": "Szko\u0142a Podstawowa w Kuleszach Ko\u015bcielnych Imieniem Kardyna\u0142a Stefana Wyszy\u0144skiego",
                "addr:country": "PL",
                "addr:postcode": "18-208",
                "addr:city": "Kulesze Ko\u015bcielne",
                "addr:street": "G\u0142\u00f3wna",
                "addr:housenumber": "2",
                "addr:teryt:simc": 400372,
                "addr:teryt:sym_ul": 5635,
                "contact:phone": "+48 862744076",
                "contact:email": "joszkol@wp.pl",
                "contact:website": "http:\/\/www.zskulesze.szkolnastrona.pl",
                "ref:regon": "000268872",
                "ref:vatin": "PL7221164867",
                "operator": "Gmina Kulesze Ko\u015bcielne",
                "operator:type": "government",
                "amenity": "school"
            }
        }
    ]
}