{"type":"FeatureCollection","features":[{"id":53590,"type":"Feature","geometry":{"type":"Point","coordinates":[19.66614,52.46129]},"properties":{"ref:rspo":53590,"official_name":"Przedszkole Niepubliczne \"Promyczek\"","name":"Przedszkole Niepubliczne \"Promyczek\"","addr:country":"PL","addr:postcode":"09-520","addr:place":"Za\u017adzierz","addr:housenumber":"33","addr:teryt:sym_ul":569757,"contact:phone":"+48 243841417","contact:email":"epromyczek@onet.pl","ref:regon":"146421984","ref:vatin":"PL7743224166","operator":"Stowarzyszenie Rozwoju Wsi Wincent\u00f3w I Okolice","operator:type":"ngo","amenity":"kindergarten"}},{"id":55088,"type":"Feature","geometry":{"type":"Point","coordinates":[19.60966,52.46581]},"properties":{"isced:level":"1;2","ref:rspo":55088,"official_name":"Szko\u0142a Podstawowa im. Ppor. Emilii Gierczak w \u0141\u0105cku","name":"Szko\u0142a Podstawowa","addr:country":"PL","addr:postcode":"09-520","addr:city":"\u0141\u0105ck","addr:street":"ul. Kolejowa","addr:housenumber":"1","addr:teryt:simc":8828,"addr:teryt:sym_ul":569562,"contact:phone":"+48 243841420","contact:email":"sp.eg@op.pl","contact:website":"http:\/\/www.glack.superszkolna.pl","ref:regon":"000268292","ref:vatin":"PL7742801696","operator":"Gmina \u0141\u0105ck","operator:type":"government","amenity":"school"}},{"id":52491,"type":"Feature","geometry":{"type":"Point","coordinates":[19.60752,52.46602]},"properties":{"ref:rspo":52491,"official_name":"Samorz\u0105dowe Przedszkole w \u0141\u0105cku","name":"Samorz\u0105dowe Przedszkole w \u0141\u0105cku","addr:country":"PL","addr:postcode":"09-520","addr:city":"\u0141\u0105ck","addr:street":"ul. Kolejowa","addr:housenumber":"5","addr:teryt:simc":8828,"addr:teryt:sym_ul":569562,"contact:phone":"+48 243841424","contact:email":"naszeprzedszkole5@wp.pl","contact:website":"http:\/\/lack.przedszkolna.net","ref:regon":"000903989","ref:vatin":"PL7742813624","operator":"Gmina \u0141\u0105ck","operator:type":"government","amenity":"kindergarten"}},{"id":277540,"type":"Feature","geometry":{"type":"Point","coordinates":[19.55074,52.67757]},"properties":{"ref:rspo":277540,"official_name":"Przedszkole w Podlasiu","name":"Przedszkole w Podlasiu","addr:country":"PL","addr:postcode":"09-520","addr:place":"Podlasie","addr:housenumber":"19","addr:teryt:sym_ul":569639,"contact:phone":"+48 243841452","contact:email":"kontakt@przedszkolewpodlasiu.pl","contact:website":"http:\/\/www.przedszkolewpodlasiu.pl","ref:regon":"389061224","operator":"Gmina \u0141\u0105ck","operator:type":"government","amenity":"kindergarten"}}]}