{
    "type": "FeatureCollection",
    "features": [
        {
            "id": 40878,
            "type": "Feature",
            "geometry": {
                "type": "Point",
                "coordinates": [
                    23.52727,
                    50.33634
                ]
            },
            "properties": {
                "isced:level": "1;2",
                "ref:rspo": 40878,
                "official_name": "Szko\u0142a Podstawowa w Machnowie Nowym",
                "name": "Szko\u0142a Podstawowa w Machnowie Nowym",
                "addr:postcode": "22-680",
                "addr:city": "Machn\u00f3w Nowy",
                "addr:street": "\u015awi\u0119tego Jana Paw\u0142a II",
                "addr:housenumber": "16",
                "addr:teryt:simc": 892978,
                "addr:teryt:sym_ul": 48913,
                "phone": "+48 846617327",
                "email": "szkolamachnow@o2.pl",
                "ref:regon": "001134671",
                "ref:vatin": "PL9211775487",
                "operator": "Gmina Lubycza Kr\u00f3lewska",
                "operator:type": "government",
                "amenity": "school"
            }
        },
        {
            "id": 41143,
            "type": "Feature",
            "geometry": {
                "type": "Point",
                "coordinates": [
                    23.5212499,
                    50.3388
                ]
            },
            "properties": {
                "ref:rspo": 41143,
                "official_name": "Przedszkole Samorz\u0105dowe w Lubyczy Kr\u00f3lewskiej",
                "name": "Przedszkole Samorz\u0105dowe w Lubyczy Kr\u00f3lewskiej",
                "addr:postcode": "22-680",
                "addr:city": "Lubycza Kr\u00f3lewska",
                "addr:street": "Parkowa",
                "addr:housenumber": "1",
                "addr:teryt:simc": 892889,
                "addr:teryt:sym_ul": 15710,
                "phone": "+48 846617177",
                "email": "przedszkolelubycza@interia.pl",
                "ref:regon": "000896611",
                "ref:vatin": "PL9211078386",
                "operator": "Gmina Lubycza Kr\u00f3lewska",
                "operator:type": "government",
                "amenity": "kindergarten"
            }
        },
        {
            "id": 64962,
            "type": "Feature",
            "geometry": {
                "type": "Point",
                "coordinates": [
                    23.52104,
                    50.3394199
                ]
            },
            "properties": {
                "isced:level": "1;2",
                "ref:rspo": 64962,
                "official_name": "Szko\u0142a Podstawowa im.genera\u0142a Nikodema Sulika",
                "name": "Szko\u0142a Podstawowa im.genera\u0142a Nikodema Sulika",
                "addr:postcode": "22-680",
                "addr:city": "Lubycza Kr\u00f3lewska",
                "addr:street": "Jana III Sobieskiego",
                "addr:housenumber": "5",
                "addr:teryt:simc": 892889,
                "addr:teryt:sym_ul": 20431,
                "phone": "+48 846617020",
                "email": "zslubycza@interia.pl",
                "ref:regon": "000269127",
                "ref:vatin": "PL9211775524",
                "operator": "Gmina Lubycza Kr\u00f3lewska",
                "operator:type": "government",
                "amenity": "school"
            }
        }
    ]
}