{
    "type": "FeatureCollection",
    "features": [
        {
            "id": 34918,
            "type": "Feature",
            "geometry": {
                "type": "Point",
                "coordinates": [
                    17.22618,
                    54.15368
                ]
            },
            "properties": {
                "isced:level": "1;2",
                "ref:rspo": 34918,
                "official_name": "Szko\u0142a Podstawowa w \u0141ubnie",
                "name": "Szko\u0142a Podstawowa w \u0141ubnie",
                "addr:postcode": "77-140",
                "addr:place": "\u0141ubno",
                "addr:housenumber": "22",
                "addr:city:simc": 746113,
                "phone": "+48 598213715",
                "email": "zswl@wp.pl",
                "website": "http:\/\/www.sp-lubno.pl",
                "ref:regon": "001141872",
                "ref:vatin": "PL8421331939",
                "operator": "Gmina Ko\u0142czyg\u0142owy",
                "operator:type": "government",
                "amenity": "school"
            }
        },
        {
            "id": 29232,
            "type": "Feature",
            "geometry": {
                "type": "Point",
                "coordinates": [
                    17.22312,
                    54.24155
                ]
            },
            "properties": {
                "ref:rspo": 29232,
                "official_name": "Gminne Przedszkole w Ko\u0142czyg\u0142owach",
                "name": "Gminne Przedszkole w Ko\u0142czyg\u0142owach",
                "addr:postcode": "77-140",
                "addr:city": "Ko\u0142czyg\u0142owy",
                "addr:street": "S\u0142upska",
                "addr:housenumber": "54",
                "addr:city:simc": 746076,
                "addr:street:sym_ul": 20316,
                "phone": "+48 598213385",
                "email": "przedszkole@kolczyglowy.pl",
                "website": "http:\/\/www.przedszkole.kolczyglowy.pl",
                "ref:regon": "000908001",
                "ref:vatin": "PL8421331796",
                "operator": "Gmina Ko\u0142czyg\u0142owy",
                "operator:type": "government",
                "amenity": "kindergarten"
            }
        },
        {
            "id": 39689,
            "type": "Feature",
            "geometry": {
                "type": "Point",
                "coordinates": [
                    17.2277999,
                    54.24224
                ]
            },
            "properties": {
                "isced:level": "1;2",
                "ref:rspo": 39689,
                "official_name": "Szko\u0142a Podstawowa w Ko\u0142czyg\u0142owach",
                "name": "Szko\u0142a Podstawowa w Ko\u0142czyg\u0142owach",
                "addr:postcode": "77-140",
                "addr:city": "Ko\u0142czyg\u0142owy",
                "addr:street": "Szkolna",
                "addr:housenumber": "10",
                "addr:city:simc": 746076,
                "addr:street:sym_ul": 21970,
                "phone": "+48 598213416",
                "email": "zskolczyglowy@gmail.com",
                "website": "http:\/\/www.zskolczyglowy.pl",
                "ref:regon": "000581770",
                "ref:vatin": "PL8421023072",
                "operator": "Gmina Ko\u0142czyg\u0142owy",
                "operator:type": "government",
                "amenity": "school"
            }
        }
    ]
}