{
    "type": "FeatureCollection",
    "features": [
        {
            "id": 131462,
            "type": "Feature",
            "geometry": {
                "type": "Point",
                "coordinates": [
                    22.62776,
                    51.67256
                ]
            },
            "properties": {
                "ref:rspo": 131462,
                "official_name": "Zesp\u00f3\u0142 Szk\u00f3\u0142 w Czemiernikach",
                "name": "Zesp\u00f3\u0142 Szk\u00f3\u0142 w Czemiernikach",
                "addr:country": "PL",
                "addr:postcode": "21-306",
                "addr:city": "Czemierniki",
                "addr:street": "ul. Kocka",
                "addr:housenumber": "45",
                "addr:teryt:simc": 8749,
                "addr:teryt:sym_ul": 11179,
                "contact:phone": "+48 833513543",
                "contact:email": "gm_sekretariat@op.pl",
                "ref:regon": "365183756",
                "operator": "Gmina Czemierniki",
                "operator:type": "government",
                "landuse": "education",
                "fixme": "amenity=school, amenity=college albo landuse=education w zale\u017cno\u015bci od tego, jakie plac\u00f3wki wchodz\u0105 w sk\u0142ad zespo\u0142u. Sprawd\u017a, kiedy stosowa\u0107 amenity=* a kiedy landuse=education.",
                "note": "Children RSPO: 13909;90220"
            }
        },
        {
            "id": 13909,
            "type": "Feature",
            "geometry": {
                "type": "Point",
                "coordinates": [
                    22.62776,
                    51.672529999999995
                ]
            },
            "properties": {
                "isced:level": "1;2",
                "ref:rspo": 13909,
                "official_name": "Szko\u0142a Podstawowa Imienia Tadeusza Ko\u015bciuszki w Czemiernikach",
                "name": "Szko\u0142a Podstawowa Imienia Tadeusza Ko\u015bciuszki w Czemiernikach",
                "addr:country": "PL",
                "addr:postcode": "21-306",
                "addr:city": "Czemierniki",
                "addr:street": "ul. Kocka",
                "addr:housenumber": "45",
                "addr:teryt:simc": 8749,
                "addr:teryt:sym_ul": 11179,
                "contact:phone": "+48 833513543",
                "contact:email": "gm_sekretariat@op.pl",
                "contact:website": "http:\/\/www.sp-czemierniki.pl",
                "ref:regon": "000266695",
                "ref:vatin": "PL5381189450",
                "operator": "Gmina Czemierniki",
                "operator:type": "government",
                "amenity": "school",
                "note": "Parent RSPO: 131462"
            }
        },
        {
            "id": 90220,
            "type": "Feature",
            "geometry": {
                "type": "Point",
                "coordinates": [
                    22.6262783,
                    51.6727485
                ]
            },
            "properties": {
                "ref:rspo": 90220,
                "official_name": "Gminne Przedszkole w Czemiernikach",
                "name": "Gminne Przedszkole w Czemiernikach",
                "addr:country": "PL",
                "addr:postcode": "21-306",
                "addr:city": "Czemierniki",
                "addr:street": "ul. Kocka",
                "addr:housenumber": "47",
                "addr:teryt:simc": 8749,
                "addr:teryt:sym_ul": 11179,
                "contact:phone": "+48 833513543",
                "contact:email": "sp_czemierniki@wp.pl",
                "contact:website": "http:\/\/www.sp-czemierniki.pl",
                "ref:regon": "000966688",
                "operator": "Gmina Czemierniki",
                "operator:type": "government",
                "amenity": "kindergarten",
                "note": "Parent RSPO: 131462"
            }
        }
    ]
}