{"type":"FeatureCollection","features":[{"id":7322,"type":"Feature","geometry":{"type":"Point","coordinates":[20.19003,50.98785]},"properties":{"isced:level":"1;2","ref:rspo":7322,"official_name":"Niepubliczna Szko\u0142a Podstawowa w Mninie","name":"Niepubliczna Szko\u0142a Podstawowa w Mninie","addr:country":"PL","addr:postcode":"26-234","addr:city":"Mnin","addr:street":"ul. Ko\u015bcielna","addr:housenumber":"38","addr:teryt:simc":9546,"addr:teryt:sym_ul":269587,"contact:phone":"+48 413911158","contact:email":"bbwrobel@wp.pl","contact:website":"http:\/\/www.nspmnin.szkolnastrona.pl","ref:regon":"260628748","operator":"Stowarzyszenie Przysz\u0142o\u015b\u0107 Dla Mnina","operator:type":"ngo","amenity":"school"}},{"id":54083,"type":"Feature","geometry":{"type":"Point","coordinates":[20.1150062,51.0077119]},"properties":{"isced:level":"1;2","ref:rspo":54083,"official_name":"Szko\u0142a Podstawowa w W\u00f3lce","name":"Szko\u0142a Podstawowa w W\u00f3lce","addr:country":"PL","addr:postcode":"26-234","addr:place":"W\u00f3lka","addr:housenumber":"4","addr:teryt:sym_ul":269854,"contact:phone":"+48 413911108","contact:email":"spwolka@o2.pl","ref:regon":"001216512","ref:vatin":"PL6581867524","operator":"Gmina S\u0142upia Konecka","operator:type":"government","amenity":"school"}},{"id":55607,"type":"Feature","geometry":{"type":"Point","coordinates":[20.0895459,51.035782]},"properties":{"isced:level":"1;2","ref:rspo":55607,"official_name":"Szko\u0142a Podstawowa w Pilczycy","name":"Szko\u0142a Podstawowa w Pilczycy","addr:country":"PL","addr:postcode":"26-234","addr:place":"Pilczyca","addr:housenumber":"70","addr:teryt:sym_ul":269682,"contact:phone":"+48 413911136","contact:email":"szkola.podstawowa2@poczta.onet.pl","contact:website":"http:\/\/www.sppilczyca.republika.pl","ref:regon":"001216446","ref:vatin":"PL6581867576","operator":"Gmina S\u0142upia Konecka","operator:type":"government","amenity":"school"}},{"id":274370,"type":"Feature","geometry":{"type":"Point","coordinates":[20.08528,51.04985]},"properties":{"ref:rspo":274370,"official_name":"Plac\u00f3wka Kszta\u0142cenia Ustawicznego Ampro","name":"Plac\u00f3wka Kszta\u0142cenia Ustawicznego Ampro","addr:country":"PL","addr:postcode":"26-234","addr:place":"Ruda Pilczycka","addr:housenumber":"23","addr:teryt:sym_ul":269736,"contact:email":"a.mlynarczyk@ampro.edu.pl","contact:website":"http:\/\/ampro.edu.pl\/","ref:regon":"385646525","operator":"Ampro Sp\u00f3\u0142ka Z Ograniczon\u0105 Odpowiedzialno\u015bci\u0105","operator:type":"private","fixme":"w zale\u017cno\u015bci od przedmiotu dzia\u0142alno\u015bci (np. amenity=training + training=*, amenity=dancing_school, amenity=language_school, amenity=music_school)"}}]}