{
    "type": "FeatureCollection",
    "features": [
        {
            "id": 27352,
            "type": "Feature",
            "geometry": {
                "type": "Point",
                "coordinates": [
                    19.57907,
                    52.71208
                ]
            },
            "properties": {
                "isced:level": "1;2",
                "ref:rspo": 27352,
                "official_name": "Szko\u0142a Podstawowa im. Adama Mickiewicza w Bo\u017cewie",
                "name": "Szko\u0142a Podstawowa",
                "addr:country": "PL",
                "addr:postcode": "09-215",
                "addr:city": "Bo\u017cewo Nowe",
                "addr:street": "Szkolna",
                "addr:housenumber": "2",
                "addr:teryt:simc": 571470,
                "addr:teryt:sym_ul": 21970,
                "contact:phone": "+48 242769119",
                "contact:email": "bozewosp@wp.pl",
                "contact:website": "http:\/\/www.spbozewo.szkolnastrona.pl",
                "ref:regon": "001113545",
                "ref:vatin": "PL7761589984",
                "operator": "Gmina Mochowo",
                "operator:type": "government",
                "amenity": "school"
            }
        },
        {
            "id": 27413,
            "type": "Feature",
            "geometry": {
                "type": "Point",
                "coordinates": [
                    19.54702,
                    52.76759
                ]
            },
            "properties": {
                "isced:level": "1;2",
                "ref:rspo": 27413,
                "official_name": "Szko\u0142a Podstawowa im. Jana Paw\u0142a II w Mochowie",
                "name": "Szko\u0142a Podstawowa",
                "addr:country": "PL",
                "addr:postcode": "09-214",
                "addr:city": "Mochowo-Parcele",
                "addr:street": "Szkolna",
                "addr:housenumber": "1",
                "addr:teryt:simc": 571458,
                "addr:teryt:sym_ul": 21970,
                "contact:phone": "+48 242763182",
                "contact:email": "spjp2mochowo@wp.pl",
                "contact:website": "http:\/\/www.spmochowo.szkolnastrona.pl",
                "ref:regon": "000630876",
                "ref:vatin": "PL7761589978",
                "operator": "Gmina Mochowo",
                "operator:type": "government",
                "amenity": "school"
            }
        },
        {
            "id": 27452,
            "type": "Feature",
            "geometry": {
                "type": "Point",
                "coordinates": [
                    19.48554,
                    52.82409
                ]
            },
            "properties": {
                "isced:level": "1;2",
                "ref:rspo": 27452,
                "official_name": "Szko\u0142a Podstawowa im.powsta\u0144c\u00f3w Styczniowych w Ligowie",
                "name": "Szko\u0142a Podstawowa im.powsta\u0144c\u00f3w Styczniowych w Ligowie",
                "addr:country": "PL",
                "addr:postcode": "09-228",
                "addr:city": "Ligowo",
                "addr:street": "Parkowa",
                "addr:housenumber": "2",
                "addr:teryt:simc": 571398,
                "addr:teryt:sym_ul": 15710,
                "contact:phone": "+48 242765160",
                "contact:email": "sekretariat.ligowo@wp.pl",
                "contact:website": "http:\/\/ligowo.szkola.pl\/",
                "ref:regon": "001113551",
                "ref:vatin": "PL7761590119",
                "operator": "Gmina Mochowo",
                "operator:type": "government",
                "amenity": "school"
            }
        }
    ]
}