{
    "type": "FeatureCollection",
    "features": [
        {
            "id": 62364,
            "type": "Feature",
            "geometry": {
                "type": "Point",
                "coordinates": [
                    20.7281799,
                    51.5761899
                ]
            },
            "properties": {
                "isced:level": "1;2",
                "ref:rspo": 62364,
                "official_name": "Publiczna Szko\u0142a Podstawowa w Kostrzyniu",
                "name": "Publiczna Szko\u0142a Podstawowa w Kostrzyniu",
                "addr:country": "PL",
                "addr:postcode": "26-811",
                "addr:place": "Kostrzyn",
                "addr:housenumber": "66A",
                "addr:teryt:sym_ul": 641992,
                "contact:phone": "+48 486156141",
                "contact:email": "pspkostrzyn@wp.pl",
                "ref:regon": "670741660",
                "ref:vatin": "PL7981478726",
                "operator": "Gmina Wy\u015bmierzyce",
                "operator:type": "government",
                "amenity": "school"
            }
        },
        {
            "id": 62365,
            "type": "Feature",
            "geometry": {
                "type": "Point",
                "coordinates": [
                    20.81362,
                    51.62467
                ]
            },
            "properties": {
                "isced:level": "1;2",
                "ref:rspo": 62365,
                "official_name": "Publiczna Szko\u0142a Podstawowa im.b\u0142.ks.prof Franciszka Ros\u0142a\u0144ca w Wy\u015bmierzycach",
                "name": "Publiczna Szko\u0142a Podstawowa im.b\u0142.ks.prof Franciszka Ros\u0142a\u0144ca w Wy\u015bmierzycach",
                "addr:country": "PL",
                "addr:postcode": "26-811",
                "addr:city": "Wy\u015bmierzyce",
                "addr:street": "Adama Mickiewicza",
                "addr:housenumber": "4",
                "addr:teryt:simc": 12740,
                "addr:teryt:sym_ul": 974044,
                "contact:phone": "+48 486157338",
                "contact:email": "u.imbor@psp.wysmierzyce.pl",
                "contact:website": "http:\/\/www.szkola.wysmierzyce.pl",
                "ref:regon": "000681359",
                "ref:vatin": "PL7981479341",
                "operator": "Gmina Wy\u015bmierzyce",
                "operator:type": "government",
                "amenity": "school"
            }
        },
        {
            "id": 62366,
            "type": "Feature",
            "geometry": {
                "type": "Point",
                "coordinates": [
                    20.82314,
                    51.62543
                ]
            },
            "properties": {
                "ref:rspo": 62366,
                "official_name": "Publiczne Przedszkole w Wy\u015bmierzycach",
                "name": "Publiczne Przedszkole w Wy\u015bmierzycach",
                "addr:country": "PL",
                "addr:postcode": "26-811",
                "addr:city": "Wy\u015bmierzyce",
                "addr:street": "Adama Mickiewicza",
                "addr:housenumber": "75",
                "addr:teryt:simc": 12740,
                "addr:teryt:sym_ul": 974044,
                "contact:phone": "+48 486157013",
                "contact:email": "k.centka@przedszkole.wysmierzyce.pl",
                "ref:regon": "670939907",
                "ref:vatin": "PL7981179722",
                "operator": "Gmina Wy\u015bmierzyce",
                "operator:type": "government",
                "amenity": "kindergarten"
            }
        }
    ]
}