{
    "type": "FeatureCollection",
    "features": [
        {
            "id": 11124,
            "type": "Feature",
            "geometry": {
                "type": "Point",
                "coordinates": [
                    18.3043898,
                    51.224657
                ]
            },
            "properties": {
                "isced:level": "1;2",
                "ref:rspo": 11124,
                "official_name": "Szko\u0142a Podstawowa w Radostowie",
                "name": "Szko\u0142a Podstawowa w Radostowie",
                "addr:postcode": "98-410",
                "addr:place": "Radost\u00f3w Pierwszy",
                "addr:housenumber": "52",
                "addr:city:simc": 196180,
                "phone": "+48 627843028",
                "email": "radostowsp@wp.pl",
                "ref:regon": "101463905",
                "operator": "Stowarzyszenie Rozwoju Wsi Radost\u00f3w",
                "operator:type": "ngo",
                "amenity": "school"
            }
        },
        {
            "id": 92997,
            "type": "Feature",
            "geometry": {
                "type": "Point",
                "coordinates": [
                    18.32696,
                    51.24062
                ]
            },
            "properties": {
                "isced:level": "1;2",
                "ref:rspo": 92997,
                "official_name": "Szko\u0142a Podstawowa w Parcicach",
                "name": "Szko\u0142a Podstawowa w Parcicach",
                "addr:postcode": "98-410",
                "addr:city": "Parcice",
                "addr:street": "Dworska",
                "addr:housenumber": "60",
                "addr:city:simc": 196150,
                "addr:street:sym_ul": 4446,
                "phone": "+48 627843134",
                "email": "spparcice@interia.pl",
                "ref:regon": "001173808",
                "ref:vatin": "PL9970152005",
                "operator": "Gmina Czastary",
                "operator:type": "government",
                "amenity": "school"
            }
        },
        {
            "id": 121960,
            "type": "Feature",
            "geometry": {
                "type": "Point",
                "coordinates": [
                    18.32233,
                    51.25897
                ]
            },
            "properties": {
                "isced:level": "1;2",
                "ref:rspo": 121960,
                "official_name": "Szko\u0142a Podstawowa im. Bohater\u00f3w Wrze\u015bnia 1939 R. w Czastarach",
                "name": "Szko\u0142a Podstawowa",
                "addr:postcode": "98-410",
                "addr:city": "Czastary",
                "addr:street": "Szkolna",
                "addr:housenumber": "4",
                "addr:city:simc": 196032,
                "addr:street:sym_ul": 21970,
                "phone": "+48 627843188",
                "email": "spczastary@wp.pl",
                "ref:regon": "000631433",
                "ref:vatin": "PL9970157095",
                "operator": "Gmina Czastary",
                "operator:type": "government",
                "amenity": "school"
            }
        },
        {
            "id": 92998,
            "type": "Feature",
            "geometry": {
                "type": "Point",
                "coordinates": [
                    18.32339,
                    51.2594
                ]
            },
            "properties": {
                "ref:rspo": 92998,
                "official_name": "Publiczne Przedszkole Samorz\u0105dowe w Czastarach",
                "name": "Publiczne Przedszkole Samorz\u0105dowe w Czastarach",
                "addr:postcode": "98-410",
                "addr:city": "Czastary",
                "addr:street": "Szkolna",
                "addr:housenumber": "5a",
                "addr:city:simc": 196032,
                "addr:street:sym_ul": 21970,
                "phone": "+48 627846463",
                "email": "przedszkole.czastary@o2.pl",
                "ref:regon": "731621450",
                "ref:vatin": "PL9970152028",
                "operator": "Gmina Czastary",
                "operator:type": "government",
                "amenity": "kindergarten"
            }
        }
    ]
}