{
    "type": "FeatureCollection",
    "features": [
        {
            "id": 263101,
            "type": "Feature",
            "geometry": {
                "type": "Point",
                "coordinates": [
                    18.77638,
                    53.2948499
                ]
            },
            "properties": {
                "ref:rspo": 263101,
                "official_name": "Przedszkole Gminne w P\u0142u\u017cnicy",
                "name": "Przedszkole Gminne w P\u0142u\u017cnicy",
                "addr:postcode": "87-214",
                "addr:place": "P\u0142u\u017cnica",
                "addr:housenumber": "55B",
                "addr:teryt:simc": 848374,
                "phone": "+48 566887131",
                "ref:regon": "368104929",
                "operator": "Gmina P\u0142u\u017cnica",
                "operator:type": "government",
                "amenity": "kindergarten",
                "note": "Parent RSPO: 263128"
            }
        },
        {
            "id": 263128,
            "type": "Feature",
            "geometry": {
                "type": "Point",
                "coordinates": [
                    18.7783906,
                    53.2960496
                ]
            },
            "properties": {
                "ref:rspo": 263128,
                "official_name": "Zesp\u00f3\u0142 Szkolno-Przedszkolny w P\u0142u\u017cnicy",
                "name": "Zesp\u00f3\u0142 Szkolno-Przedszkolny w P\u0142u\u017cnicy",
                "addr:postcode": "87-214",
                "addr:place": "P\u0142u\u017cnica",
                "addr:housenumber": "43",
                "addr:teryt:simc": 848374,
                "phone": "+48 566887131",
                "email": "zespolszkol@pluznica.pl",
                "website": "http:\/\/www.szkola.pluznica.info",
                "ref:regon": "368109163",
                "operator": "Gmina P\u0142u\u017cnica",
                "operator:type": "government",
                "landuse": "education",
                "fixme": "amenity=school, amenity=college albo landuse=education w zale\u017cno\u015bci od tego, jakie plac\u00f3wki wchodz\u0105 w sk\u0142ad zespo\u0142u. Sprawd\u017a, kiedy stosowa\u0107 amenity=* a kiedy landuse=education.",
                "note": "Children RSPO: 85160;263101"
            }
        },
        {
            "id": 85160,
            "type": "Feature",
            "geometry": {
                "type": "Point",
                "coordinates": [
                    18.7783906,
                    53.2960196
                ]
            },
            "properties": {
                "isced:level": "1;2",
                "ref:rspo": 85160,
                "official_name": "Szko\u0142a Podstawowa w P\u0142u\u017cnicy",
                "name": "Szko\u0142a Podstawowa w P\u0142u\u017cnicy",
                "addr:postcode": "87-214",
                "addr:place": "P\u0142u\u017cnica",
                "addr:housenumber": "43",
                "addr:door": "n",
                "addr:teryt:simc": 848374,
                "phone": "+48 566887131",
                "email": "zespolszkol@pluznica.pl",
                "website": "http:\/\/szkola.pluznica.info",
                "ref:regon": "000562867",
                "ref:vatin": "PL8781632910",
                "operator": "Gmina P\u0142u\u017cnica",
                "operator:type": "government",
                "amenity": "school",
                "note": "Parent RSPO: 263128"
            }
        }
    ]
}