{
    "type": "FeatureCollection",
    "features": [
        {
            "id": 10167,
            "type": "Feature",
            "geometry": {
                "type": "Point",
                "coordinates": [
                    20.81311,
                    53.53598
                ]
            },
            "properties": {
                "ref:rspo": 10167,
                "official_name": "Zesp\u00f3\u0142 Szk\u00f3\u0142 w Jedwabnie",
                "name": "Zesp\u00f3\u0142 Szk\u00f3\u0142 w Jedwabnie",
                "addr:postcode": "12-122",
                "addr:city": "Jedwabno",
                "addr:street": "Polna",
                "addr:housenumber": "1",
                "addr:city:simc": 476560,
                "addr:street:sym_ul": 17011,
                "phone": "+48 896213078",
                "email": "sekretariat@zsjedwabno.pl",
                "website": "http:\/\/zsjedwabno.edupage.org",
                "ref:regon": "510887155",
                "ref:vatin": "PL7451683654",
                "operator": "Gmina Jedwabno",
                "operator:type": "government",
                "landuse": "education",
                "fixme": "amenity=school, amenity=college albo landuse=education w zale\u017cno\u015bci od tego, jakie plac\u00f3wki wchodz\u0105 w sk\u0142ad zespo\u0142u. Sprawd\u017a, kiedy stosowa\u0107 amenity=* a kiedy landuse=education.",
                "note": "Children RSPO: 70521;70523"
            }
        },
        {
            "id": 70521,
            "type": "Feature",
            "geometry": {
                "type": "Point",
                "coordinates": [
                    20.81311,
                    53.53595
                ]
            },
            "properties": {
                "isced:level": "1;2",
                "ref:rspo": 70521,
                "official_name": "Szko\u0142a Podstawowa im. Komisji Edukacji Narodowej",
                "name": "Szko\u0142a Podstawowa",
                "addr:postcode": "12-122",
                "addr:city": "Jedwabno",
                "addr:street": "Polna",
                "addr:housenumber": "1",
                "addr:city:simc": 476560,
                "addr:street:sym_ul": 17011,
                "phone": "+48 896213078",
                "email": "sekretariat@zsjedwabno.pl",
                "website": "http:\/\/zsjedwabno.edupage.org",
                "ref:regon": "519453903",
                "ref:vatin": "PL7451683654",
                "operator": "Gmina Jedwabno",
                "operator:type": "government",
                "amenity": "school",
                "note": "Parent RSPO: 10167"
            }
        },
        {
            "id": 70523,
            "type": "Feature",
            "geometry": {
                "type": "Point",
                "coordinates": [
                    20.81311,
                    53.535920000000004
                ]
            },
            "properties": {
                "ref:rspo": 70523,
                "official_name": "Przedszkole w Jedwabnie",
                "name": "Przedszkole w Jedwabnie",
                "addr:postcode": "12-122",
                "addr:city": "Jedwabno",
                "addr:street": "Polna",
                "addr:housenumber": "1",
                "addr:city:simc": 476560,
                "addr:street:sym_ul": 17011,
                "phone": "+48 896213078",
                "email": "sekretariat@zsjedwabno.pl",
                "website": "http:\/\/zsjedwabno.edupage.org",
                "ref:regon": "519487227",
                "ref:vatin": "PL7451683654",
                "operator": "Gmina Jedwabno",
                "operator:type": "government",
                "amenity": "kindergarten",
                "note": "Parent RSPO: 10167"
            }
        }
    ]
}