{"type":"FeatureCollection","features":[{"id":21818,"type":"Feature","geometry":{"type":"Point","coordinates":[16.18322,52.52875]},"properties":{"isced:level":"1;2","ref:rspo":21818,"official_name":"Szko\u0142a Podstawowa im. Konstytucji 3 Maja w Luboszu","name":"Szko\u0142a Podstawowa","addr:country":"PL","addr:postcode":"64-423","addr:city":"Lubosz","addr:street":"ul. Powsta\u0144c\u00f3w Wielkopolskich","addr:housenumber":"1","addr:teryt:simc":17377,"addr:teryt:sym_ul":587867,"contact:email":"szkola.lubosz@wp.pl","contact:website":"http:\/\/www.splubosz.neostrada.pl","ref:regon":"001227668","ref:vatin":"PL7871016746","operator":"Gmina Kwilcz","operator:type":"government","amenity":"school"}},{"id":23191,"type":"Feature","geometry":{"type":"Point","coordinates":[16.0841299,52.55203]},"properties":{"isced:level":"1;2","ref:rspo":23191,"official_name":"Szko\u0142a Podstawowa im. Tadeusza Ko\u015bciuszki w Kwilczu","name":"Szko\u0142a Podstawowa","addr:country":"PL","addr:postcode":"64-420","addr:city":"Kwilcz","addr:street":"ul. Kardyna\u0142a Stefana Wyszy\u0144skiego","addr:housenumber":"20","addr:teryt:simc":35421,"addr:teryt:sym_ul":587809,"contact:phone":"+48 612915241","contact:email":"szkola@spkwilcz.pl","contact:website":"http:\/\/www.spkwilcz.superszkolna.pl","ref:regon":"000600473","ref:vatin":"PL5951398447","operator":"Gmina Kwilcz","operator:type":"government","amenity":"school"}},{"id":21971,"type":"Feature","geometry":{"type":"Point","coordinates":[16.08381,52.5568]},"properties":{"ref:rspo":21971,"official_name":"Przedszkole \"Pod Topol\u0105\" w Kwilczu","name":"Przedszkole \"Pod Topol\u0105\" w Kwilczu","addr:country":"PL","addr:postcode":"64-420","addr:city":"Kwilcz","addr:street":"ul. Gumna","addr:housenumber":"13","addr:teryt:simc":6373,"addr:teryt:sym_ul":587809,"contact:email":"przedszkole.kwilcz@interia.pl","contact:website":"http:\/\/www.przedszkolekwilcz.c0.pl","ref:regon":"631578822","ref:vatin":"PL7871016663","operator":"Gmina Kwilcz","operator:type":"government","amenity":"kindergarten"}}]}