{
    "type": "FeatureCollection",
    "features": [
        {
            "id": 21818,
            "type": "Feature",
            "geometry": {
                "type": "Point",
                "coordinates": [
                    16.18322,
                    52.52875
                ]
            },
            "properties": {
                "isced:level": "1;2",
                "ref:rspo": 21818,
                "official_name": "Szko\u0142a Podstawowa im. Konstytucji 3 Maja w Luboszu",
                "name": "Szko\u0142a Podstawowa",
                "addr:postcode": "64-423",
                "addr:city": "Lubosz",
                "addr:street": "Powsta\u0144c\u00f3w Wielkopolskich",
                "addr:housenumber": "1",
                "addr:teryt:simc": 587867,
                "addr:teryt:sym_ul": 17377,
                "email": "szkola.lubosz@wp.pl",
                "website": "http:\/\/www.splubosz.neostrada.pl",
                "ref:regon": "001227668",
                "ref:vatin": "PL7871016746",
                "operator": "Gmina Kwilcz",
                "operator:type": "government",
                "amenity": "school"
            }
        },
        {
            "id": 23191,
            "type": "Feature",
            "geometry": {
                "type": "Point",
                "coordinates": [
                    16.0841299,
                    52.55203
                ]
            },
            "properties": {
                "isced:level": "1;2",
                "ref:rspo": 23191,
                "official_name": "Szko\u0142a Podstawowa im. Tadeusza Ko\u015bciuszki w Kwilczu",
                "name": "Szko\u0142a Podstawowa",
                "addr:postcode": "64-420",
                "addr:city": "Kwilcz",
                "addr:street": "Kardyna\u0142a Stefana Wyszy\u0144skiego",
                "addr:housenumber": "20",
                "addr:teryt:simc": 587809,
                "addr:teryt:sym_ul": 35421,
                "phone": "+48 612915241",
                "email": "szkola@spkwilcz.pl",
                "website": "http:\/\/www.spkwilcz.superszkolna.pl",
                "ref:regon": "000600473",
                "ref:vatin": "PL5951398447",
                "operator": "Gmina Kwilcz",
                "operator:type": "government",
                "amenity": "school"
            }
        },
        {
            "id": 21971,
            "type": "Feature",
            "geometry": {
                "type": "Point",
                "coordinates": [
                    16.08381,
                    52.5568
                ]
            },
            "properties": {
                "ref:rspo": 21971,
                "official_name": "Przedszkole \"Pod Topol\u0105\" w Kwilczu",
                "name": "Przedszkole \"Pod Topol\u0105\" w Kwilczu",
                "addr:postcode": "64-420",
                "addr:city": "Kwilcz",
                "addr:street": "Gumna",
                "addr:housenumber": "13",
                "addr:teryt:simc": 587809,
                "addr:teryt:sym_ul": 6373,
                "email": "przedszkole.kwilcz@interia.pl",
                "website": "http:\/\/www.przedszkolekwilcz.c0.pl",
                "ref:regon": "631578822",
                "ref:vatin": "PL7871016663",
                "operator": "Gmina Kwilcz",
                "operator:type": "government",
                "amenity": "kindergarten"
            }
        }
    ]
}