{
    "type": "FeatureCollection",
    "features": [
        {
            "id": 63478,
            "type": "Feature",
            "geometry": {
                "type": "Point",
                "coordinates": [
                    22.20822,
                    53.3205
                ]
            },
            "properties": {
                "isced:level": "1;2",
                "ref:rspo": 63478,
                "official_name": "Szko\u0142a Filialna w Jurcu Szlacheckim",
                "name": "Szko\u0142a Filialna w Jurcu Szlacheckim",
                "addr:postcode": "18-520",
                "addr:place": "Jurzec Szlachecki",
                "addr:housenumber": "53",
                "addr:teryt:simc": 406446,
                "phone": "+48 862785056",
                "email": "spstawiski@wp.pl",
                "website": "http:\/\/www.spstawiski.pl",
                "ref:regon": "263478000",
                "ref:vatin": "PL7211143102",
                "operator": "Gmina Stawiski",
                "operator:type": "government",
                "amenity": "school",
                "note": "Parent RSPO: 57829"
            }
        },
        {
            "id": 57830,
            "type": "Feature",
            "geometry": {
                "type": "Point",
                "coordinates": [
                    22.06772,
                    53.35607
                ]
            },
            "properties": {
                "isced:level": "1;2",
                "ref:rspo": 57830,
                "official_name": "Szko\u0142a Podstawowa w Porytem",
                "name": "Szko\u0142a Podstawowa w Porytem",
                "addr:postcode": "18-520",
                "addr:city": "Poryte",
                "addr:street": "Szkolna",
                "addr:housenumber": "23",
                "addr:teryt:simc": 990907,
                "addr:teryt:sym_ul": 21970,
                "phone": "+48 862788682",
                "email": "poryte-23@wp.pl",
                "website": "http:\/\/www.spporyte.stawiski.pl",
                "ref:regon": "001129380",
                "ref:vatin": "PL2910081396",
                "operator": "Gmina Stawiski",
                "operator:type": "government",
                "amenity": "school"
            }
        },
        {
            "id": 59166,
            "type": "Feature",
            "geometry": {
                "type": "Point",
                "coordinates": [
                    22.16123,
                    53.37907
                ]
            },
            "properties": {
                "ref:rspo": 59166,
                "official_name": "Miejskie Przedszkole w Stawiskach",
                "name": "Miejskie Przedszkole w Stawiskach",
                "addr:postcode": "18-520",
                "addr:city": "Stawiski",
                "addr:street": "Cedrowska",
                "addr:housenumber": "1",
                "addr:teryt:simc": 957548,
                "addr:teryt:sym_ul": 2567,
                "phone": "+48 862785651",
                "email": "stawiski.przedszkole@wp.pl",
                "ref:regon": "450000431",
                "ref:vatin": "PL2910081321",
                "operator": "Gmina Stawiski",
                "operator:type": "government",
                "amenity": "kindergarten"
            }
        },
        {
            "id": 57829,
            "type": "Feature",
            "geometry": {
                "type": "Point",
                "coordinates": [
                    22.15906,
                    53.38069
                ]
            },
            "properties": {
                "isced:level": "1;2",
                "ref:rspo": 57829,
                "official_name": "Szko\u0142a Podstawowa im. Tadeusza Ko\u015bciuszki w Stawiskach",
                "name": "Szko\u0142a Podstawowa",
                "addr:postcode": "18-520",
                "addr:city": "Stawiski",
                "addr:street": "Polowa",
                "addr:housenumber": "12",
                "addr:teryt:simc": 957548,
                "addr:teryt:sym_ul": 17027,
                "phone": "+48 862785609",
                "email": "spstawiski@wp.pl",
                "website": "http:\/\/www.spstawiski.pl",
                "ref:regon": "000263478",
                "ref:vatin": "PL7211143102",
                "operator": "Gmina Stawiski",
                "operator:type": "government",
                "amenity": "school",
                "note": "Children RSPO: 63478"
            }
        }
    ]
}