{"type":"FeatureCollection","features":[{"id":4103,"type":"Feature","geometry":{"type":"Point","coordinates":[18.78907,52.70331]},"properties":{"isced:level":"3","ref:rspo":4103,"official_name":"Centrum Edukacji I Kszta\u0142cenia Kadr Trzyletnie Liceum Og\u00f3lnokszta\u0142c\u0105ce dla Doros\u0142ych w B\u0105dkowie","name":"Centrum Edukacji I Kszta\u0142cenia Kadr Trzyletnie Liceum Og\u00f3lnokszta\u0142c\u0105ce dla Doros\u0142ych w B\u0105dkowie","addr:country":"PL","addr:postcode":"87-704","addr:city":"B\u0105dkowo","addr:street":"ul. W\u0142oc\u0142awska","addr:housenumber":"13","addr:teryt:simc":24504,"addr:teryt:sym_ul":858160,"contact:phone":"+48 542724051","ref:regon":"341314987","ref:vatin":"PL8791298708","operator":"Dane Do Uzupe\u0142nienia","operator:type":"private","amenity":"school"}},{"id":84267,"type":"Feature","geometry":{"type":"Point","coordinates":[18.78907,52.70328]},"properties":{"ref:rspo":84267,"official_name":"Zesp\u00f3\u0142 Szkolno-Przedszkolny w B\u0105dkowie","name":"Zesp\u00f3\u0142 Szkolno-Przedszkolny w B\u0105dkowie","addr:country":"PL","addr:postcode":"87-704","addr:city":"B\u0105dkowo","addr:street":"ul. W\u0142oc\u0142awska","addr:housenumber":"13","addr:teryt:simc":24504,"addr:teryt:sym_ul":858160,"contact:phone":"+48 542332618","contact:email":"spbadkowo@interia.pl","contact:website":"http:\/\/www.szkolabadkowo.pl","ref:regon":"341176835","ref:vatin":"PL8911620935","operator":"Gmina B\u0105dkowo","operator:type":"government","landuse":"education","fixme":"amenity=school, amenity=college albo landuse=education w zale\u017cno\u015bci od tego, jakie plac\u00f3wki wchodz\u0105 w sk\u0142ad zespo\u0142u. Sprawd\u017a, kiedy stosowa\u0107 amenity=* a kiedy landuse=education.","note":"Children RSPO: 109953;114878"}},{"id":109953,"type":"Feature","geometry":{"type":"Point","coordinates":[18.78907,52.703250000000004]},"properties":{"isced:level":"1;2","ref:rspo":109953,"official_name":"Szko\u0142a Podstawowa w B\u0105dkowie","name":"Szko\u0142a Podstawowa w B\u0105dkowie","addr:country":"PL","addr:postcode":"87-704","addr:city":"B\u0105dkowo","addr:street":"ul. W\u0142oc\u0142awska","addr:housenumber":"13","addr:teryt:simc":24504,"addr:teryt:sym_ul":858160,"contact:phone":"+48 542332618","contact:email":"spbadkowo@interia.pl","contact:website":"http:\/\/www.szkolabadkowo.pl","ref:regon":"000637039","ref:vatin":"PL8911426216","operator":"Gmina B\u0105dkowo","operator:type":"government","amenity":"school","note":"Parent RSPO: 84267"}},{"id":114878,"type":"Feature","geometry":{"type":"Point","coordinates":[18.78907,52.70322]},"properties":{"ref:rspo":114878,"official_name":"Przedszkole Samorz\u0105dowe w B\u0105dkowie","name":"Przedszkole Samorz\u0105dowe w B\u0105dkowie","addr:country":"PL","addr:postcode":"87-704","addr:city":"B\u0105dkowo","addr:street":"ul. W\u0142oc\u0142awska","addr:housenumber":"13","addr:teryt:simc":24504,"addr:teryt:sym_ul":858160,"contact:phone":"+48 542332618","contact:email":"spbadkowo@interia.pl","contact:website":"http:\/\/www.szkolabadkowo.pl","ref:regon":"910004628","ref:vatin":"PL8911428824","operator":"Gmina B\u0105dkowo","operator:type":"government","amenity":"kindergarten","note":"Parent RSPO: 84267"}}]}