{"type":"FeatureCollection","features":[{"id":60258,"type":"Feature","geometry":{"type":"Point","coordinates":[19.30122,51.1281]},"properties":{"isced:level":"1;2","ref:rspo":60258,"official_name":"Publiczna Szko\u0142a Podstawowa w Woli Blakowej","name":"Publiczna Szko\u0142a Podstawowa w Woli Blakowej","addr:country":"PL","addr:postcode":"97-565","addr:place":"Wola Blakowa","addr:housenumber":"39","addr:teryt:sym_ul":544409,"contact:phone":"+48 446801387","contact:email":"pspwolablakowa@lgotawielka.pl","ref:regon":"001139875","ref:vatin":"PL7722121604","operator":"Gmina Lgota Wielka","operator:type":"government","amenity":"school"}},{"id":60273,"type":"Feature","geometry":{"type":"Point","coordinates":[19.32811,51.15013]},"properties":{"ref:rspo":60273,"official_name":"Przedszkole Samorz\u0105dowe w Lgocie Wielkiej","name":"Przedszkole Samorz\u0105dowe w Lgocie Wielkiej","addr:country":"PL","addr:postcode":"97-565","addr:city":"Lgota Wielka","addr:street":"ul. Szkolna","addr:housenumber":"3","addr:teryt:simc":21970,"addr:teryt:sym_ul":544355,"contact:phone":"+48 601742180","contact:email":"przedszkole@lgotawielka.pl","ref:regon":"100935762","ref:vatin":"PL7722383089","operator":"Gmina Lgota Wielka","operator:type":"government","amenity":"kindergarten"}},{"id":60943,"type":"Feature","geometry":{"type":"Point","coordinates":[19.32811,51.150099999999995]},"properties":{"isced:level":"1;2","ref:rspo":60943,"official_name":"Publiczna Szko\u0142a Podstawowa im. M. Konopnickiej w Lgocie Wielkiej","name":"Publiczna Szko\u0142a Podstawowa","addr:country":"PL","addr:postcode":"97-565","addr:city":"Lgota Wielka","addr:street":"ul. Szkolna","addr:housenumber":"3","addr:door":"-","addr:teryt:simc":21970,"addr:teryt:sym_ul":544355,"contact:phone":"+48 446801389","contact:email":"psplgotawielka@lgotawielka.pl","contact:website":"http:\/\/www.psplgotawielka.naszbip.pl","ref:regon":"590730626","ref:vatin":"PL7722409044","operator":"Gmina Lgota Wielka","operator:type":"government","amenity":"school"}},{"id":58154,"type":"Feature","geometry":{"type":"Point","coordinates":[19.33845,51.17234]},"properties":{"isced:level":"1;2","ref:rspo":58154,"official_name":"Publiczna Szko\u0142a Podstawowa w Brudzicach","name":"Publiczna Szko\u0142a Podstawowa w Brudzicach","addr:country":"PL","addr:postcode":"97-565","addr:city":"Brudzice","addr:street":"ul. Radomszcza\u0144ska","addr:housenumber":"1","addr:teryt:simc":18317,"addr:teryt:sym_ul":544243,"contact:phone":"+48 446801312","contact:email":"pspbrudzice@lgotawielka.pl","ref:regon":"590730632","ref:vatin":"PL7722121627","operator":"Gmina Lgota Wielka","operator:type":"government","amenity":"school"}}]}