{
    "type": "FeatureCollection",
    "features": [
        {
            "id": 26173,
            "type": "Feature",
            "geometry": {
                "type": "Point",
                "coordinates": [
                    19.69262,
                    51.0950599
                ]
            },
            "properties": {
                "isced:level": "1;2",
                "ref:rspo": 26173,
                "official_name": "Publiczna Szko\u0142a Podstawowa w Rzejowicach",
                "name": "Publiczna Szko\u0142a Podstawowa w Rzejowicach",
                "addr:postcode": "97-512",
                "addr:place": "Kolonia Rzejowice",
                "addr:housenumber": "91",
                "addr:city:simc": 543634,
                "phone": "+48 446819076",
                "email": "sprzejowice@wikom.pl",
                "ref:regon": "001139250",
                "ref:vatin": "PL7722122213",
                "operator": "Gmina Kodr\u0105b",
                "operator:type": "government",
                "amenity": "school"
            }
        },
        {
            "id": 70856,
            "type": "Feature",
            "geometry": {
                "type": "Point",
                "coordinates": [
                    19.63317,
                    51.10437
                ]
            },
            "properties": {
                "isced:level": "1;2",
                "ref:rspo": 70856,
                "official_name": "Publiczna Szko\u0142a Podstawowa w Kodr\u0119bie",
                "name": "Publiczna Szko\u0142a Podstawowa w Kodr\u0119bie",
                "addr:postcode": "97-512",
                "addr:city": "Kodr\u0105b",
                "addr:street": "Le\u015bna",
                "addr:housenumber": "2",
                "addr:city:simc": 543516,
                "addr:street:sym_ul": 10898,
                "phone": "+48 446819326",
                "email": "pspkodrab@wikom.pl",
                "website": "https:\/\/pspkodrab.wikom.pl",
                "ref:regon": "000756554",
                "ref:vatin": "PL7722413695",
                "operator": "Gmina Kodr\u0105b",
                "operator:type": "government",
                "amenity": "school"
            }
        }
    ]
}